Workbook

Sheet Sheet1
A1: 📘 Most Common RAR Codes for Non-Covered Denials (Deep Explanation)
A5: 1️⃣ N115 — Service Not Covered Unless Medical Criteria Met
A7: Meaning
A9: Service may be covered only if medical necessity guidelines are met, but payer determined criteria were not satisfied.
A11: Real Scenarios
A13: MRI without conservative therapy documentation
A15: Lab test without supporting diagnosis
A17: Sleep study without symptoms
A19: Therapy beyond allowed visits without justification
A21: Root Cause
A23: Diagnosis not supporting CPT
A25: Missing documentation
... A381: EMR integration

Sheet Sheet2
A1: CARC CODE | B1: DENIAL REASON | C1: RARC / REMARKS | D1: MEANING & EXAMPLES | E1: REAL SCENARIOS | F1: ROOT CAUSE | G1: RESOLUTION STEPS | H1: Code
A2: CO 18 | B2: Duplicate | C2: N522 — Duplicate of a claim processed, as a crossover claim. | D2: The claim is an exact duplicate of one already processed or in process (same patient, date of service, provider, codes, etc.). No payment issued; often seen in general duplicates or Medicare crossover cases where claim was auto-forwarded. | E2: • Resubmitted identical claim by mistake or due to system glitch. • Billed same procedure twice without modifier (e.g., two identical office visits same day). • Submitted to secondary payer while primary (e.g., Medicare) processes/crossover pending. • Billing system auto-follow-up triggered duplicate. • Corrected claim sent without proper replacement indicator. | F2: • Provider billed secondary payer prematurely before crossover completed • Duplicate claim submission from billing system • Patient insurance sequence not verified properly | G2: • Check Medicare crossover confirmation (ERA/EOB remark) • Confirm if secondary payer received claim via crossover • Do not rebill if crossover pending or completed • Rebill only if crossover failed and payer confirms resubmission required • Adjust duplicate claim if already processed | H2: =SUBSTITUTE( "<tr data-carc=""" & A2 & """ data-rarc=""" & C2 & """" & CHAR(10) & " data-denial=""" & SUBSTITUTE(TRIM(D2),CHAR(10),"\n") & """" & CHAR(10) & " data-root=""" & SUBSTITUTE(TRIM(F2),CHAR(10),"\n") & """>" & CHAR(10) & " <td><span class=""carc-badge co"">" & A2 & "</span></td>" & CHAR(10) & " <td style=""font-weight:500;"">" & B2 & "</td>" & CHAR(10) & " <td class=""rarc-wrap""><div class=""rarc-id"">" & LEFT(C2,FIND(" ",C2)-1) & "</div><div class=""rarc-desc"">" & TRIM(MID(C2,FIND("—",C2)+1,999)) & "</div></td>" & CHAR(10) & " <td class=""td-sm"">" & SUBSTITUTE(TRIM(D2),CHAR(10),"<br>") & "</td>" & CHAR(10) & " <td><div class=""chip-row""><span class=""chip chip-red"">" & SUBSTITUTE(SUBSTITUTE(SUBSTITUTE(TRIM(E2),"• ",""),CHAR(10),"|"),"|", "</span><span class=""chip chip-red"">") & "</span></div></td>" & CHAR(10) & " <td><div class=""chip-row""><span class=""chip chip-red"">" & SUBSTITUTE(SUBSTITUTE(SUBSTITUTE(TRIM(F2),"• ",""),CHAR(10),"|"),"|", "</span><span class=""chip chip-red"">") & "</span></div></td>" & CHAR(10) & " <td class=""td-sm"">" & SUBSTITUTE(TRIM(G2),CHAR(10),"<br>") & "</td>" & CHAR(10) & " </tr>","""","""") -> <tr data-carc="CO 18" data-rarc="N522 — Duplicate of a claim processed, as a crossover claim." data-denial="The claim is an exact duplicate of one already processed or in process (same patient, date of service, provider, codes, etc.). No payment issued; often seen in general duplicates or Medicare crossover cases where claim was auto-forwarded." data-root="• Provider billed secondary payer prematurely before crossover completed\n• Duplicate claim submission from billing system\n• Patient insurance sequence not verified properly"> <td><span class="carc-badge co">CO 18</span></td> <td style="font-weight:500;">Duplicate</td> <td class="rarc-wrap"><div class="rarc-id">N522</div><div class="rarc-desc">Duplicate of a claim processed, as a crossover claim.</div></td> <td class="td-sm">The claim is an exact duplicate of one already processed or in process (same patient, date of service, provider, codes, etc.). No payment issued; often seen in general duplicates or Medicare crossover cases where claim was auto-forwarded.</td> <td><div class="chip-row"><span class="chip chip-red">Resubmitted identical claim by mistake or due to system glitch.</span><span class="chip chip-red">Billed same procedure twice without modifier (e.g., two identical office visits same day).</span><span class="chip chip-red">Submitted to secondary payer while primary (e.g., Medicare) processes/crossover pending.</span><span class="chip chip-red">Billing system auto-follow-up triggered duplicate.</span><span class="chip chip-red">Corrected claim sent without proper replacement indicator.</span></div></td> <td><div class="chip-row"><span class="chip chip-red">Provider billed secondary payer prematurely before crossover completed</span><span class="chip chip-red">Duplicate claim submission from billing system</span><span class="chip chip-red">Patient insurance sequence not verified properly</span></div></td> <td class="td-sm">• Check Medicare crossover confirmation (ERA/EOB remark)<br>• Confirm if secondary payer received claim via crossover<br>• Do not rebill if crossover pending or completed<br>• Rebill only if crossover failed and payer confirms resubmission required<br>• Adjust duplicate claim if already processed</td> </tr>
A3: PR 1 | B3: Deductible Amount | C3: PR (Patient Responsibility) | D3: The payer applied the allowed amount (or portion) to the patient's annual deductible. The patient is responsible for this amount until the deductible is met; no payer payment issued for that portion. | E3: • Patient has not met their yearly deductible (e.g., $1,500 plan deductible; first claims of the year applied here). High-deductible health plan (HDHP) services billed early in the year. • Secondary payer applies after primary meets its deductible. Claim for preventive service that doesn't count toward deductible, but others do. • Billing system shows zero payer payment due to unmet deductible. | F3: Patient hasn't met deductible yet (common at start of plan year or high-deductible plans). Incorrect eligibility verification missing deductible status. Failure to collect estimated patient responsibility upfront. Coordination of benefits (COB) where primary deductible not satisfied. | G3: ✔ Verify patient deductible status via eligibility check/portal (pre-service). ✔ Bill patient directly for the PR-1 amount (post to patient ledger). ✔ If error (e.g., deductible already met), appeal with proof from payer. ✔ Collect payment from patient or set up payment plan. ✔ Update billing system with correct deductible info for future claims. | H3: =SUBSTITUTE( "<tr data-carc=""" & A3 & """ data-rarc=""" & C3 & """" & CHAR(10) & " data-denial=""" & SUBSTITUTE(TRIM(D3),CHAR(10),"\n") & """" & CHAR(10) & " data-root=""" & SUBSTITUTE(TRIM(F3),CHAR(10),"\n") & """>" & CHAR(10) & " <td><span class=""carc-badge co"">" & A3 & "</span></td>" & CHAR(10) & " <td style=""font-weight:500;"">" & B3 & "</td>" & CHAR(10) & " <td class=""rarc-wrap""><div class=""rarc-id"">" & LEFT(C3,FIND(" ",C3)-1) & "</div><div class=""rarc-desc"">" & TRIM(MID(C3,FIND("—",C3)+1,999)) & "</div></td>" & CHAR(10) & " <td class=""td-sm"">" & SUBSTITUTE(TRIM(D3),CHAR(10),"<br>") & "</td>" & CHAR(10) & " <td><div class=""chip-row""><span class=""chip chip-red"">" & SUBSTITUTE(SUBSTITUTE(SUBSTITUTE(TRIM(E3),"• ",""),CHAR(10),"|"),"|", "</span><span class=""chip chip-red"">") & "</span></div></td>" & CHAR(10) & " <td><div class=""chip-row""><span class=""chip chip-red"">" & SUBSTITUTE(SUBSTITUTE(SUBSTITUTE(TRIM(F3),"• ",""),CHAR(10),"|"),"|", "</span><span class=""chip chip-red"">") & "</span></div></td>" & CHAR(10) & " <td class=""td-sm"">" & SUBSTITUTE(TRIM(G3),CHAR(10),"<br>") & "</td>" & CHAR(10) & " </tr>","""","""") -> #VALUE!
A4: PR 2 | B4: Coinsurance Amount | C4: PR (Patient Responsibility) | D4: After deductible is met, the patient is responsible for their percentage share (coinsurance) of the allowed amount (e.g., 20% patient / 80% payer). Payer pays its portion; patient owes the rest. | E4: • Patient pays 20% coinsurance on specialist visit after deductible met. • Surgical procedure where plan is 80/20 after deductible. • Outpatient services with coinsurance applied to allowed amount. • Secondary payer coinsurance on remaining balance after primary payment. | F4: Standard plan design requires patient coinsurance share. Deductible met but coinsurance not collected upfront. Misunderstanding of plan benefits during eligibility check. COB where secondary applies coinsurance. | G4: ✔ Confirm coinsurance percentage via payer portal/eligibility. ✔ Bill patient for the PR-2 amount shown on EOB. ✔ If disputed (e.g., wrong percentage), appeal with benefit details. ✔ Post to patient account and follow up for payment. | H4: =SUBSTITUTE( "<tr data-carc=""" & A4 & """ data-rarc=""" & C4 & """" & CHAR(10) & " data-denial=""" & SUBSTITUTE(TRIM(D4),CHAR(10),"\n") & """" & CHAR(10) & " data-root=""" & SUBSTITUTE(TRIM(F4),CHAR(10),"\n") & """>" & CHAR(10) & " <td><span class=""carc-badge co"">" & A4 & "</span></td>" & CHAR(10) & " <td style=""font-weight:500;"">" & B4 & "</td>" & CHAR(10) & " <td class=""rarc-wrap""><div class=""rarc-id"">" & LEFT(C4,FIND(" ",C4)-1) & "</div><div class=""rarc-desc"">" & TRIM(MID(C4,FIND("—",C4)+1,999)) & "</div></td>" & CHAR(10) & " <td class=""td-sm"">" & SUBSTITUTE(TRIM(D4),CHAR(10),"<br>") & "</td>" & CHAR(10) & " <td><div class=""chip-row""><span class=""chip chip-red"">" & SUBSTITUTE(SUBSTITUTE(SUBSTITUTE(TRIM(E4),"• ",""),CHAR(10),"|"),"|", "</span><span class=""chip chip-red"">") & "</span></div></td>" & CHAR(10) & " <td><div class=""chip-row""><span class=""chip chip-red"">" & SUBSTITUTE(SUBSTITUTE(SUBSTITUTE(TRIM(F4),"• ",""),CHAR(10),"|"),"|", "</span><span class=""chip chip-red"">") & "</span></div></td>" & CHAR(10) & " <td class=""td-sm"">" & SUBSTITUTE(TRIM(G4),CHAR(10),"<br>") & "</td>" & CHAR(10) & " </tr>","""","""") -> #VALUE!
A5: PR 3 | B5: Copay Amount | C5: PR (Patient Responsibility) | D5: A fixed flat fee the patient must pay for a specific covered service (e.g., $30 office visit copay), regardless of allowed amount. Payer pays the balance after copay. | E5: • $25 copay for primary care visit. • $50 ER copay applied to emergency service. • Tiered copays (e.g., $10 generic Rx vs. $50 specialist). • Copay waived incorrectly for preventive care but applied elsewhere. | F5: Plan requires fixed copay per service type/visit. Copay not collected at time of service. Error in copay waiver verification (e.g., for preventive). Multiple visits/services triggering separate copays. | G5: ✔ Check EOB for exact copay amount and service applied to. ✔ Bill patient directly for PR-3 amount. ✔ If waiver error, appeal with documentation (e.g., preventive service). ✔ Pursue patient payment promptly. | H5: =SUBSTITUTE( "<tr data-carc=""" & A5 & """ data-rarc=""" & C5 & """" & CHAR(10) & " data-denial=""" & SUBSTITUTE(TRIM(D5),CHAR(10),"\n") & """" & CHAR(10) & " data-root=""" & SUBSTITUTE(TRIM(F5),CHAR(10),"\n") & """>" & CHAR(10) & " <td><span class=""carc-badge co"">" & A5 & "</span></td>" & CHAR(10) & " <td style=""font-weight:500;"">" & B5 & "</td>" & CHAR(10) & " <td class=""rarc-wrap""><div class=""rarc-id"">" & LEFT(C5,FIND(" ",C5)-1) & "</div><div class=""rarc-desc"">" & TRIM(MID(C5,FIND("—",C5)+1,999)) & "</div></td>" & CHAR(10) & " <td class=""td-sm"">" & SUBSTITUTE(TRIM(D5),CHAR(10),"<br>") & "</td>" & CHAR(10) & " <td><div class=""chip-row""><span class=""chip chip-red"">" & SUBSTITUTE(SUBSTITUTE(SUBSTITUTE(TRIM(E5),"• ",""),CHAR(10),"|"),"|", "</span><span class=""chip chip-red"">") & "</span></div></td>" & CHAR(10) & " <td><div class=""chip-row""><span class=""chip chip-red"">" & SUBSTITUTE(SUBSTITUTE(SUBSTITUTE(TRIM(F5),"• ",""),CHAR(10),"|"),"|", "</span><span class=""chip chip-red"">") & "</span></div></td>" & CHAR(10) & " <td class=""td-sm"">" & SUBSTITUTE(TRIM(G5),CHAR(10),"<br>") & "</td>" & CHAR(10) & " </tr>","""","""") -> #VALUE!

Sheet Calculate
A1: CARC | B1: Reason | C1: RARC | D1: MEANING & EXAMPLES | E1: REAL SCENARIOS | F1: ROOT CAUSE | G1: RESOLUTION STEPS | H1: Code | I1: With Formula Code
A2: CO 16 | B2: Additional Documentation Required to Process Claim | C2: N425—Additional documentation is needed to process this claim. At a minimum, send the information identified in this notice. | D2: The claim is pending or denied because the payer requires additional documentation to complete processing. This is not always a final denial—it is often a request for information (RFI) indicating that the payer cannot determine: Medical necessity Eligibility Authorization compliance Accuracy of billed services The payer will typically specify minimum required documents in the notice. Failure to submit the requested information within the timeframe may result in a full denial. | E2: Payer requests medical records for review → documentation not submitted → claim denied. Operative report required for procedure validation → missing → claim pended. Authorization proof requested but not provided → processing delayed. Incomplete clinical notes submitted → insufficient → denial issued. Incorrect documents uploaded (wrong patient/encounter) → claim not processed. | F2: Visits exceed physician-certified limits. Plan of care not updated or recertified. Mismatch between documentation and billing. Failure to track authorized visit counts. Staff unaware of certification limitations. | G2: Review payer notice to identify required documentation. Collect all relevant records, such as: Progress notes Operative reports Physician orders Authorization details Test results Validate documentation for completeness and accuracy. Submit documents via correct payer channel (portal, fax, EDI). Include claim reference details (claim number, patient info). Track submission and confirm receipt. Follow up until claim is processed. | I2: <tr data-carc="" data-type="" data-rarc="N425 — Statutorily excluded service(s)." data-denial="" data-root=""><td><div class="row-num">#561</div><span class="carc-badge "></span></td><td><span class="denial-reason"></span></td><td class="rarc-wrap"><div class="rarc-id">N425</div><div class="rarc-desc">Statutorily excluded service(s).</div></td><td class="td-meaning"></td><td><div class="chip-row"></div></td><td><div class="chip-row"></div></td><td class="td-res"></td></tr>
A3: CO 4 | B3: Add-on code | C3: N122—Missing/incomplete/invalid length of transport | D3: The claim was denied because an add-on procedure code (+ symbol in CPT, e.g., +11045, +69990) was billed alone without its required primary/base procedure code on the same claim. Add-on codes are never payable independently; they must accompany the primary service they supplement. | E3: • 49568 (hernia mesh implantation) billed alone without a primary hernia repair code (e.g., 49560–49566) → denied. • 15777 (grafting for wound closure) submitted without the primary closure/reconstruction code (e.g., 13100–13160 series). • 69990 (microsurgical techniques) billed by itself instead of with the primary neurosurgical or ENT procedure. • 99199 (unlisted special service) or +95972 (complex programming of neurostimulator) submitted standalone → rejected. • 95971 (simple programming of neurostimulator) billed without the primary implantation code (e.g., 64555, 64561). • Anesthesia add-on time code or time-based add-on (e.g., +99354 prolonged service) submitted without base code. | F3: • Add-on code (+XXXXX) submitted without corresponding primary/base procedure code. • Primary code omitted, on different claim, or not billed on same date of service. • Billing software or manual entry error (add-on code selected alone). • Provider unaware add-on codes require primary code on same claim. • Coding error: Misidentifying an add-on code as standalone or forgetting to pair it. • Claim split or resubmission error: Primary code processed earlier; add-on billed later without reference. • Lack of pre-billing check for required primary code linkage per CPT guidelines. | G3: • Identify add-on code from EOB and confirm primary code needed (CPT book or NCCI lookup). • Verify primary procedure was performed and billed (same DOS, same claim). • Resubmit corrected claim including both primary and add-on codes (frequency 7). • If primary code already billed separately → appeal with claim history and documentation showing linkage. • Accept denial if no primary procedure performed (post write-off). | I3: <tr data-carc="CO 4" data-type="co" data-rarc="N122 — Add-on code cannot be billed by itself." data-denial="The claim was denied because an add-on procedure code (+ symbol in CPT, e.g., +11045, +69990) was billed alone without its required primary/base procedure code on the same claim. Add-on codes are never payable independently; they must accompany the primary service they supplement." data-root="• Add-on code (+XXXXX) submitted without corresponding primary/base procedure code.\n• Primary code omitted, on different claim, or not billed on same date of service.\n• Billing software or manual entry error (add-on code selected alone).\n• Provider unaware add-on codes require primary code on same claim.\n• Coding error: Misidentifying an add-on code as standalone or forgetting to pair it.\n• Claim split or resubmission error: Primary code processed earlier; add-on billed later without reference.\n• Lack of pre-billing check for required primary code linkage per CPT guidelines."><td><div class="row-num">#43</div><span class="carc-badge co">CO 4</span></td><td><span class="denial-reason">Add-on code</span></td><td class="rarc-wrap"><div class="rarc-id">N122</div><div class="rarc-desc">Add-on code cannot be billed by itself.</div></td><td class="td-meaning">The claim was denied because an add-on procedure code (+ symbol in CPT, e.g., +11045, +69990) was billed alone without its required primary/base procedure code on the same claim. Add-on codes are never payable independently; they must accompany the primary service they supplement.</td><td><div class="chip-row"><span class="chip chip-green">49568 (hernia mesh implantation) billed alone without a primary hernia repair code (e.g., 49560–49566) → denied.</span><span class="chip chip-green">15777 (grafting for wound closure) submitted without the primary closure/reconstruction code (e.g., 13100–13160 series).</span><span class="chip chip-green">69990 (microsurgical techniques) billed by itself instead of with the primary neurosurgical or ENT procedure.</span><span class="chip chip-green">99199 (unlisted special service) or +95972 (complex programming of neurostimulator) submitted standalone → rejected.</span><span class="chip chip-green">95971 (simple programming of neurostimulator) billed without the primary implantation code (e.g., 64555, 64561).</span><span class="chip chip-green">Anesthesia add-on time code or time-based add-on (e.g., +99354 prolonged service) submitted without base code.</span></div></td><td><div class="chip-row"><span class="chip chip-green">Add-on code (+XXXXX) submitted without corresponding primary/base procedure code.</span><span class="chip chip-green">Primary code omitted, on different claim, or not billed on same date of service.</span><span class="chip chip-green">Billing software or manual entry error (add-on code selected alone).</span><span class="chip chip-green">Provider unaware add-on codes require primary code on same claim.</span><span class="chip chip-green">Coding error: Misidentifying an add-on code as standalone or forgetting to pair it.</span><span class="chip chip-green">Claim split or resubmission error: Primary code processed earlier; add-on billed later without reference.</span><span class="chip chip-green">Lack of pre-billing check for required primary code linkage per CPT guidelines.</span></div></td><td class="td-res">• Identify add-on code from EOB and confirm primary code needed (CPT book or NCCI lookup).<br>• Verify primary procedure was performed and billed (same DOS, same claim).<br>• Resubmit corrected claim including both primary and add-on codes (frequency 7).<br>• If primary code already billed separately → appeal with claim history and documentation showing linkage.<br>• Accept denial if no primary procedure performed (post write-off).</td></tr>
A4: CO 4 | B4: Adjustment Due to Use of Non-Specific Procedure Code | C4: MA91—Alert: An adjustment was made because a more specific procedure code should have been billed | D4: This alert indicates that the claim was adjusted because a more specific procedure code should have been billed. The submitted CPT/HCPCS code was considered too general, non-specific, or not the most appropriate code for the service rendered. | E4: Unlisted or generic CPT code used when a specific code exists → claim adjusted. Broad procedure code billed instead of detailed code → reduced payment. Incorrect code selection despite available specific HCPCS → denial applied. Use of miscellaneous code without justification → claim rejected. Coding not updated to reflect current CPT specificity → adjustment issued. | F4: Use of non-specific or generic procedure codes. Lack of awareness of updated CPT/HCPCS codes. Incomplete coding knowledge or training. Failure to review coding guidelines. System defaults to general codes. Insufficient documentation to support specific code selection. | G4: Review clinical documentation for accurate coding. Identify the most specific CPT/HCPCS code applicable. Replace generic or incorrect code with appropriate specific code. Resubmit corrected claim if necessary. Appeal if correct code was used and supported by documentation. | I4: <tr data-carc="" data-type="" data-rarc="MA91 — Alert: This determination is the result of the appeal you filed." data-denial="" data-root=""><td><div class="row-num">#224</div><span class="carc-badge "></span></td><td><span class="denial-reason"></span></td><td class="rarc-wrap"><div class="rarc-id">MA91</div><div class="rarc-desc">Alert: This determination is the result of the appeal you filed.</div></td><td class="td-meaning"></td><td><div class="chip-row"></div></td><td><div class="chip-row"></div></td><td class="td-res"></td></tr>
A5: CO 151 | B5: Anesthesia Time Exceeds Allowed Maximum for Procedure | C5: N194—Anesthesia time exceeds the established maximum for this procedure | D5: The claim was adjusted or denied because the reported anesthesia time exceeds the maximum allowable time established by the payer for the specific procedure. Payers use standard anesthesia time guidelines, base units, and medical necessity criteria to determine appropriate reimbursement. If the billed time is significantly higher than expected for the procedure, the payer may reduce payment or deny the excess time as not reasonable or necessary. On the CMS-1500 claim form, anesthesia services are reported in Box 24D — CPT/HCPCS Codes (anesthesia codes) and Box 24G — Units (time units), which must align with documented anesthesia time. On the UB-04 claim form, anesthesia-related services may be reported in Form Locator (FL) 44 — HCPCS Code and FL 46 — Units, subject to payer limits. | E5: Anesthesia time billed significantly longer than typical for procedure → excess units denied. Incorrect time calculation (start/stop time error) → overbilling detected. Duplicate or overlapping anesthesia time submitted → adjustment applied. Procedure completed quickly but excessive time billed → denial issued. Documentation does not support billed anesthesia duration → claim reduced. | F5: Anesthesia time exceeds payer-established limits. Incorrect calculation of anesthesia time units. Documentation does not support billed duration. Duplicate or overlapping time entries. Lack of awareness of payer anesthesia guidelines. System or billing errors in unit reporting. | G5: Review anesthesia record for accurate start and end times. Verify correct calculation of time units per payer guidelines. Ensure documentation supports billed anesthesia duration. Correct units if overreported and resubmit claim. Appeal if extended time is medically necessary and documented. | I5: <tr data-carc="" data-type="" data-rarc="N194 — Technical component not paid if provider does not own the equipment used." data-denial="" data-root=""><td><div class="row-num">#315</div><span class="carc-badge "></span></td><td><span class="denial-reason"></span></td><td class="rarc-wrap"><div class="rarc-id">N194</div><div class="rarc-desc">Technical component not paid if provider does not own the equipment used.</div></td><td class="td-meaning"></td><td><div class="chip-row"></div></td><td><div class="chip-row"></div></td><td class="td-res"></td></tr>
A6: CO 45 | B6: ASC Quality Reporting Program Compliance | C6: N551—Alert: Payment adjusted based on a penalty for late filing | D6: The payment for this claim was adjusted based on the Ambulatory Surgical Center (ASC) Quality Reporting (ASCQR) Program) requirements. Under this Medicare program, ASCs must submit specified quality data measures to CMS. On the UB-04 claim form, ASC facility services are reported using Form Locator (FL) 4 — Type of Bill (usually 83X for ASC), FL 42 — Revenue Code, and FL 44 — HCPCS/Rate/HIPPS Code, which determine payment under the ASC fee schedule. Professional services billed on the CMS-1500 use Box 24D — Procedure Code for surgical services, but the quality reporting adjustment typically affects the facility payment. | E6: ASC failed to submit required quality reporting data → payment reduced. Incomplete submission of ASC quality measures → adjustment applied. Facility missed CMS reporting deadline → reimbursement penalty applied. ASC submitted incorrect or invalid reporting data → payment impacted. Quality reporting non-compliance detected during CMS review → claim adjusted. | F6: Failure to submit required ASCQR quality reporting measures. Incomplete or inaccurate quality data submission. Missed CMS reporting deadlines. Lack of internal tracking of reporting requirements. Miscommunication between clinical quality team and billing department. System not configured to capture required reporting data. | G6: Verify ASC participation status in the ASC Quality Reporting Program. Review CMS quality reporting submission records for compliance. Confirm whether the adjustment reflects a reporting penalty. Coordinate with quality/compliance team to address reporting gaps. Appeal only if the reporting data was submitted correctly but not recognized. | I6: <tr data-carc="" data-type="" data-rarc="N551 — Payment adjusted based on the Ambulatory Surgical Center (ASC) Quality Reporting Program." data-denial="" data-root=""><td><div class="row-num">#688</div><span class="carc-badge "></span></td><td><span class="denial-reason"></span></td><td class="rarc-wrap"><div class="rarc-id">N551</div><div class="rarc-desc">Payment adjusted based on the Ambulatory Surgical Center (ASC) Quality Reporting Program.</div></td><td class="td-meaning"></td><td><div class="chip-row"></div></td><td><div class="chip-row"></div></td><td class="td-res"></td></tr>
A7: CO 119 | B7: Benefit Exhausted | C7: N365—This benefit has been exhausted | D7: The claim was denied or adjusted because the patient has exhausted the available benefits for this service under their insurance plan. This means the patient has reached the maximum allowable limit, which may be based on number of visits, units, or total dollar amount within a defined benefit period. Once the benefit limit is reached, the payer will no longer reimburse for additional services of that type under the current plan period. | E7: Physical therapy visits exceed annual limit → additional visits denied. Chiropractic services exceed covered sessions → no payment issued. Mental health benefits reach maximum → further claims denied. DME benefit cap reached → additional rentals not covered. Dollar-based benefit maximum exceeded → claim denied. | F7: Benefit maximum reached (visits, units, or dollar limit). High utilization of limited services. Failure to track remaining benefits. Lack of eligibility and benefit verification. Plan-specific coverage limits exceeded. | G7: Verify benefit usage and remaining limits with payer. Confirm that benefit maximum has been reached. Check for secondary insurance or alternate coverage. Inform patient of financial responsibility. Appeal only if benefit exhaustion was applied incorrectly.
A8: CO 119 | B8: Benefit Exhausted for the Service | C8: N215—Alert: Under your applicable benefit plan, benefits have been exhausted for this service | D8: This alert indicates that benefits for the specific service have been exhausted under the patient’s plan. The payer has determined that the patient has already reached the maximum allowable limit (e.g., visit limits, dollar limits, or service caps) for this benefit. As a result, no further payment will be made for additional services of this type under the current plan. | E8: Physical therapy visit limit reached → additional visits denied. Chiropractic care exceeds annual maximum → no payment issued. Mental health sessions exceed plan limit → claim denied. DME rental capped → further billing not covered. Service utilization exceeds dollar or unit cap → denial applied. | F8: Physical therapy visit limit reached → additional visits denied. Chiropractic care exceeds annual maximum → no payment issued. Mental health sessions exceed plan limit → claim denied. DME rental capped → further billing not covered. Service utilization exceeds dollar or unit cap → denial applied. | G8: Benefit maximum limit reached. High utilization of limited services. Lack of tracking of remaining benefits. Failure to verify benefit limits prior to service. Plan-specific service caps exceeded. | I8: <tr data-carc="" data-type="" data-rarc="N215 — Alert: A payer providing supplemental or secondary coverage shall not require a claims determination for this service from a primary payer as a condition of making its own claims determination." data-denial="" data-root=""><td><div class="row-num">#338</div><span class="carc-badge "></span></td><td><span class="denial-reason"></span></td><td class="rarc-wrap"><div class="rarc-id">N215</div><div class="rarc-desc">Alert: A payer providing supplemental or secondary coverage shall not require a claims determination for this service from a primary payer as a condition of making its own claims determination.</div></td><td class="td-meaning"></td><td><div class="chip-row"></div></td><td><div class="chip-row"></div></td><td class="td-res"></td></tr>
A9: CO 119 | B9: Benefit Maximum | C9: M90—Not covered when performed more than once within a 12-month period | D9: The claim was denied because the payer allows coverage for this service only once within a 12-month period, and records indicate the patient already received the same or similar service during that timeframe. Frequency limitations are applied to prevent duplicate or unnecessary services unless medical necessity or exception criteria are met. | E9: • Annual screening test billed twice within the same year → denied. • Preventive exam performed again before 12 months from prior visit → denial issued. • Diagnostic service repeated within frequency window without medical necessity → denied. • DME supply replacement billed earlier than annual allowance → denial applied. • Procedure submitted again due to scheduling error or duplicate billing → payer denies second claim. | F9: • Service repeated within payer frequency limitation period. • Failure to verify patient service history prior to billing or scheduling. • Missing documentation supporting medical necessity for repeat service. • Incorrect coding (screening vs diagnostic) triggering frequency edit. • Duplicate claim submission or resubmission without correction indicator. • Staff unaware of payer frequency rules. | G9: • Review prior claim history and confirm date of previously paid service. • Determine whether repeat service qualifies for medical necessity exception. • If appropriate → appeal with documentation supporting necessity or clinical indication. • Correct coding if service should be diagnostic rather than routine screening. • If denial valid → transfer responsibility to patient only if proper notification obtained. • Adjust or void duplicate claim if submitted in error. | I9: <tr data-carc="CO 119" data-type="co" data-rarc="M90 — Not covered more than once in a 12 month period." data-denial="The claim was denied because the payer allows coverage for this service only once within a 12-month period, and records indicate the patient already received the same or similar service during that timeframe. Frequency limitations are applied to prevent duplicate or unnecessary services unless medical necessity or exception criteria are met." data-root="• Service repeated within payer frequency limitation period.\n• Failure to verify patient service history prior to billing or scheduling.\n• Missing documentation supporting medical necessity for repeat service.\n• Incorrect coding (screening vs diagnostic) triggering frequency edit.\n• Duplicate claim submission or resubmission without correction indicator.\n• Staff unaware of payer frequency rules."><td><div class="row-num">#133</div><span class="carc-badge co">CO 119</span></td><td><span class="denial-reason">Benefit Maximum</span></td><td class="rarc-wrap"><div class="rarc-id">M90</div><div class="rarc-desc">Not covered more than once in a 12 month period.</div></td><td class="td-meaning">The claim was denied because the payer allows coverage for this service only once within a 12-month period, and records indicate the patient already received the same or similar service during that timeframe. Frequency limitations are applied to prevent duplicate or unnecessary services unless medical necessity or exception criteria are met.</td><td><div class="chip-row"><span class="chip chip-green">Annual screening test billed twice within the same year → denied.</span><span class="chip chip-green">Preventive exam performed again before 12 months from prior visit → denial issued.</span><span class="chip chip-green">Diagnostic service repeated within frequency window without medical necessity → denied.</span><span class="chip chip-green">DME supply replacement billed earlier than annual allowance → denial applied.</span><span class="chip chip-green">Procedure submitted again due to scheduling error or duplicate billing → payer denies second claim.</span></div></td><td><div class="chip-row"><span class="chip chip-green">Service repeated within payer frequency limitation period.</span><span class="chip chip-green">Failure to verify patient service history prior to billing or scheduling.</span><span class="chip chip-green">Missing documentation supporting medical necessity for repeat service.</span><span class="chip chip-green">Incorrect coding (screening vs diagnostic) triggering frequency edit.</span><span class="chip chip-green">Duplicate claim submission or resubmission without correction indicator.</span><span class="chip chip-green">Staff unaware of payer frequency rules.</span></div></td><td class="td-res">• Review prior claim history and confirm date of previously paid service.<br>• Determine whether repeat service qualifies for medical necessity exception.<br>• If appropriate → appeal with documentation supporting necessity or clinical indication.<br>• Correct coding if service should be diagnostic rather than routine screening.<br>• If denial valid → transfer responsibility to patient only if proper notification obtained.<br>• Adjust or void duplicate claim if submitted in error.</td></tr>
A10: CO 119 | B10: Benefit Maximum | C10: N362—The number of Days or Units of Service exceeds our acceptable maximum | D10: The claim was denied or adjusted because the billed number of days, units, visits, or services exceeds the payer's allowable maximum limit for a specified time period, benefit category, or per-episode/per-year cap. The payer enforces strict quantitative restrictions (e.g., maximum visits per year, units per day, sessions per authorization) as defined in the patient's benefit plan, medical policy, or coverage guidelines. | E10: • Physical therapy billed 30 units/visits; plan limits 20 per year → denied for 10 excess units. • Home health aide services billed 45 days in episode; Medicare or plan caps at 30 days → excess days denied. • Chiropractic adjustments billed 40 visits; payer allows maximum 26 per year → denied for 14 over limit. • Mental health therapy sessions (e.g., 90837) billed 25 per year; benefit max 15 → excess sessions patient responsibility. • Dialysis sessions or infusion therapy exceed per-month or per-episode cap → over-limit units adjusted. | F10: • Billed units/days/visits exceed the plan's hard limit (per year, per episode, per authorization, or per lifetime). • No prior check of benefit maximums during eligibility verification or pre-service authorization. • Authorization approved for fewer units/days than billed (e.g., auth for 12 PT visits; billed 18). • Benefit cap reset not accounted for (e.g., new calendar year but patient used prior-year limit). • Billing software or superbills not tracking or flagging benefit maximums per patient/plan. • Provider continued services beyond plan limit without patient consent or additional authorization. | G10: • Verify billed units/days against the cap and any prior authorization limits (check auth letter or payer portal). • If error in billing (e.g., typo in units) → Correct claim to stay within limit and resubmit (frequency 7 replacement/corrected). • If excess justified (e.g., medical necessity) → Appeal with documentation (e.g., progress notes, physician letter justifying additional units) and request exception. • If limit reached → Post write-off for excess amount; bill patient for over-limit portion (after notifying and obtaining consent). • Obtain retroactive authorization for additional units if payer allows; resubmit once updated. | I10: <tr data-carc="CO 119" data-type="co" data-rarc="N362 — The number of Days or Units of Service exceeds our acceptable maximum." data-denial="The claim was denied or adjusted because the billed number of days, units, visits, or services exceeds the payer's allowable maximum limit for a specified time period, benefit category, or per-episode/per-year cap. The payer enforces strict quantitative restrictions (e.g., maximum visits per year, units per day, sessions per authorization) as defined in the patient's benefit plan, medical policy, or coverage guidelines." data-root="• Billed units/days/visits exceed the plan's hard limit (per year, per episode, per authorization, or per lifetime).\n• No prior check of benefit maximums during eligibility verification or pre-service authorization.\n• Authorization approved for fewer units/days than billed (e.g., auth for 12 PT visits; billed 18).\n• Benefit cap reset not accounted for (e.g., new calendar year but patient used prior-year limit).\n• Billing software or superbills not tracking or flagging benefit maximums per patient/plan.\n• Provider continued services beyond plan limit without patient consent or additional authorization."><td><div class="row-num">#47</div><span class="carc-badge co">CO 119</span></td><td><span class="denial-reason">Benefit Maximum</span></td><td class="rarc-wrap"><div class="rarc-id">N362</div><div class="rarc-desc">The number of Days or Units of Service exceeds our acceptable maximum.</div></td><td class="td-meaning">The claim was denied or adjusted because the billed number of days, units, visits, or services exceeds the payer's allowable maximum limit for a specified time period, benefit category, or per-episode/per-year cap. The payer enforces strict quantitative restrictions (e.g., maximum visits per year, units per day, sessions per authorization) as defined in the patient's benefit plan, medical policy, or coverage guidelines.</td><td><div class="chip-row"><span class="chip chip-green">Physical therapy billed 30 units/visits; plan limits 20 per year → denied for 10 excess units.</span><span class="chip chip-green">Home health aide services billed 45 days in episode; Medicare or plan caps at 30 days → excess days denied.</span><span class="chip chip-green">Chiropractic adjustments billed 40 visits; payer allows maximum 26 per year → denied for 14 over limit.</span><span class="chip chip-green">Mental health therapy sessions (e.g., 90837) billed 25 per year; benefit max 15 → excess sessions patient responsibility.</span><span class="chip chip-green">Dialysis sessions or infusion therapy exceed per-month or per-episode cap → over-limit units adjusted.</span></div></td><td><div class="chip-row"><span class="chip chip-green">Billed units/days/visits exceed the plan's hard limit (per year, per episode, per authorization, or per lifetime).</span><span class="chip chip-green">No prior check of benefit maximums during eligibility verification or pre-service authorization.</span><span class="chip chip-green">Authorization approved for fewer units/days than billed (e.g., auth for 12 PT visits; billed 18).</span><span class="chip chip-green">Benefit cap reset not accounted for (e.g., new calendar year but patient used prior-year limit).</span><span class="chip chip-green">Billing software or superbills not tracking or flagging benefit maximums per patient/plan.</span><span class="chip chip-green">Provider continued services beyond plan limit without patient consent or additional authorization.</span></div></td><td class="td-res">• Verify billed units/days against the cap and any prior authorization limits (check auth letter or payer portal).<br>• If error in billing (e.g., typo in units) → Correct claim to stay within limit and resubmit (frequency 7 replacement/corrected).<br>• If excess justified (e.g., medical necessity) → Appeal with documentation (e.g., progress notes, physician letter justifying additional units) and request exception.<br>• If limit reached → Post write-off for excess amount; bill patient for over-limit portion (after notifying and obtaining consent).<br>• Obtain retroactive authorization for additional units if payer allows; resubmit once updated.</td></tr>
A11: CO 119 | B11: Benefit Maximum Reached | C11: N131—Alert: Total payments under this benefit have reached the benefit maximum. Submit future claims to the next plan tier. | D11: This alert indicates that the total allowable payments under the current benefit plan have reached the maximum limit. | E11: Physical therapy visits exceed annual limit → further claims denied. Chiropractic care maximum reached → no additional payment under plan. Mental health session cap exceeded → claim denied for remaining visits. Patient transitions from primary plan to secondary tier → billing shift required. Benefit exhausted mid-treatment → remaining services not covered under current plan. | F11: Benefit maximum limit reached under plan. High utilization of limited services (e.g., therapy visits). Lack of tracking of benefit usage. No awareness of plan-specific limits. Failure to verify remaining benefits before service | G11: Verify benefit usage and maximum limits with payer. Identify if secondary or next-tier coverage is available. Submit subsequent claims to appropriate payer/plan tier. Inform patient of benefit exhaustion and financial responsibility. Appeal only if benefit maximum was applied incorrectly. | I11: <tr data-carc="" data-type="" data-rarc="N131 — Total payments under multiple contracts cannot exceed the allowance for this service." data-denial="" data-root=""><td><div class="row-num">#259</div><span class="carc-badge "></span></td><td><span class="denial-reason"></span></td><td class="rarc-wrap"><div class="rarc-id">N131</div><div class="rarc-desc">Total payments under multiple contracts cannot exceed the allowance for this service.</div></td><td class="td-meaning"></td><td><div class="chip-row"></div></td><td><div class="chip-row"></div></td><td class="td-res"></td></tr>
A12: CO 119 | B12: Benefit Payments Ending Due to Expiration of Payment Cycle | C12: N132—Alert: Payments will cease for this benefit upon the expiration of this payment cycle. | D12: This alert indicates that payments for this benefit will stop once the current payment cycle or benefit period expires. | E12: Therapy services covered until end of annual benefit cycle → future visits denied after expiration. Home health episode nearing end date → payments cease after cycle completion. Contractual benefit period ending → no further reimbursement beyond cycle. Patient continues treatment beyond covered timeframe → claims denied. Payer notifies provider of upcoming benefit termination → alert issued. | F12: Benefit tied to a defined payment cycle or timeframe. Approaching end of coverage period (annual, episode-based, or contractual). Lack of awareness of benefit expiration timelines. Failure to track benefit periods. Continued services beyond covered timeframe. | G12: Verify benefit period and expiration date with payer. Ensure services are billed within active coverage period. Identify alternative coverage or next benefit tier if available. Inform patient of upcoming benefit expiration. Adjust treatment or billing plan accordingly. Appeal only if payment cycle was applied incorrectly. | I12: <tr data-carc="" data-type="" data-rarc="N132 — Alert: Payments will cease for services rendered by this US Government debarred or excluded provider after the 30 day grace period as previously notified." data-denial="" data-root=""><td><div class="row-num">#260</div><span class="carc-badge "></span></td><td><span class="denial-reason"></span></td><td class="rarc-wrap"><div class="rarc-id">N132</div><div class="rarc-desc">Alert: Payments will cease for services rendered by this US Government debarred or excluded provider after the 30 day grace period as previously notified.</div></td><td class="td-meaning"></td><td><div class="chip-row"></div></td><td><div class="chip-row"></div></td><td class="td-res"></td></tr>
A13: CO 97 | B13: Bundling | C13: M14—The patient has a condition previously denied for this procedure/service | D13: No separate payment allowed for an injection given during an office visit. If the patient only received an injection (no significant E/M service), the office visit is also not payable. The injection is bundled into the visit or considered the primary service. | E13: • Patient seen only for injection (e.g., corticosteroid 20610) → E/M visit (99213) denied. • Office visit + injection billed; payer bundles injection into visit → no separate payment for injection. • Minor E/M + therapeutic injection same day → E/M denied if not significant/separately identifiable. | F13: • Injection billed separately when considered part of office visit. • No significant, separately identifiable E/M service documented (missing -25 modifier). • Patient visit solely for injection → no billable E/M component. • Provider unaware of bundling rules for injections during office visits. | G13: • Review documentation: Confirm if significant E/M occurred (history, exam, decision-making beyond injection). • If significant E/M → resubmit with -25 modifier on E/M code. • If only injection → accept denial for E/M and keep injection payment (or vice versa). • Appeal with detailed notes proving separate E/M service if -25 justified. | I13: <tr data-carc="CO 97" data-type="co" data-rarc="M14 — No separate payment for an injection administered during an office visit, and no payment for a full office visit if the patient only received an injection." data-denial="No separate payment allowed for an injection given during an office visit. If the patient only received an injection (no significant E/M service), the office visit is also not payable. The injection is bundled into the visit or considered the primary service." data-root="• Injection billed separately when considered part of office visit.\n• No significant, separately identifiable E/M service documented (missing -25 modifier).\n• Patient visit solely for injection → no billable E/M component.\n• Provider unaware of bundling rules for injections during office visits."><td><div class="row-num">#78</div><span class="carc-badge co">CO 97</span></td><td><span class="denial-reason">Bundling</span></td><td class="rarc-wrap"><div class="rarc-id">M14</div><div class="rarc-desc">No separate payment for an injection administered during an office visit, and no payment for a full office visit if the patient only received an injection.</div></td><td class="td-meaning">No separate payment allowed for an injection given during an office visit. If the patient only received an injection (no significant E/M service), the office visit is also not payable. The injection is bundled into the visit or considered the primary service.</td><td><div class="chip-row"><span class="chip chip-green">Patient seen only for injection (e.g., corticosteroid 20610) → E/M visit (99213) denied.</span><span class="chip chip-green">Office visit + injection billed; payer bundles injection into visit → no separate payment for injection.</span><span class="chip chip-green">Minor E/M + therapeutic injection same day → E/M denied if not significant/separately identifiable.</span></div></td><td><div class="chip-row"><span class="chip chip-green">Injection billed separately when considered part of office visit.</span><span class="chip chip-green">No significant, separately identifiable E/M service documented (missing -25 modifier).</span><span class="chip chip-green">Patient visit solely for injection → no billable E/M component.</span><span class="chip chip-green">Provider unaware of bundling rules for injections during office visits.</span></div></td><td class="td-res">• Review documentation: Confirm if significant E/M occurred (history, exam, decision-making beyond injection).<br>• If significant E/M → resubmit with -25 modifier on E/M code.<br>• If only injection → accept denial for E/M and keep injection payment (or vice versa).<br>• Appeal with detailed notes proving separate E/M service if -25 justified.</td></tr>
A14: CO 16 | B14: Bundling | C14: M12—Diagnostic tests performed by a physician who also provided the interpretation must indicate whether the test was purchased or performed | D14: Physician must indicate on the claim if any part of the diagnostic test (technical component) was purchased/outsourced. | E14: • ECG or X-ray global billing without marking purchased services. • Lab/radiology outsourced; claim lacks indicator. • Interpretation-only billing without disclosing purchased component. | F14: • Box 20 (CMS-1500) left blank or “No” when services were purchased. • No equivalent indicator on UB-04 (FL 39–41 or remarks). • Billing software did not prompt for purchased service disclosure. | G14: • Check Box 20 on CMS-1500 (or UB-04 equivalent) for purchased services indicator. • Correct claim: Mark “Yes” in Box 20 (CMS-1500) and enter purchased amount if required. • Resubmit corrected claim (frequency 7). • Appeal with documentation showing purchased vs. performed components. | I14: <tr data-carc="CO 16" data-type="co" data-rarc="M12 — Diagnostic tests performed by a physician must indicate whether purchased services are included on the claim." data-denial="Physician must indicate on the claim if any part of the diagnostic test (technical component) was purchased/outsourced." data-root="• Box 20 (CMS-1500) left blank or “No” when services were purchased.\n• No equivalent indicator on UB-04 (FL 39–41 or remarks).\n• Billing software did not prompt for purchased service disclosure."><td><div class="row-num">#66</div><span class="carc-badge co">CO 16</span></td><td><span class="denial-reason">Bundling</span></td><td class="rarc-wrap"><div class="rarc-id">M12</div><div class="rarc-desc">Diagnostic tests performed by a physician must indicate whether purchased services are included on the claim.</div></td><td class="td-meaning">Physician must indicate on the claim if any part of the diagnostic test (technical component) was purchased/outsourced.</td><td><div class="chip-row"><span class="chip chip-green">ECG or X-ray global billing without marking purchased services.</span><span class="chip chip-green">Lab/radiology outsourced; claim lacks indicator.</span><span class="chip chip-green">Interpretation-only billing without disclosing purchased component.</span></div></td><td><div class="chip-row"><span class="chip chip-green">Box 20 (CMS-1500) left blank or “No” when services were purchased.</span><span class="chip chip-green">No equivalent indicator on UB-04 (FL 39–41 or remarks).</span><span class="chip chip-green">Billing software did not prompt for purchased service disclosure.</span></div></td><td class="td-res">• Check Box 20 on CMS-1500 (or UB-04 equivalent) for purchased services indicator.<br>• Correct claim: Mark “Yes” in Box 20 (CMS-1500) and enter purchased amount if required.<br>• Resubmit corrected claim (frequency 7).<br>• Appeal with documentation showing purchased vs. performed components.</td></tr>
A15: CO 97 | B15: Bundling | C15: M3—Equipment is the same or similar to equipment already being used | D15: The claim was denied because the payer determined that the Durable Medical Equipment (DME) being billed is the same as, or similar to, equipment the patient already owns or is currently renting. Coverage is not allowed for duplicate or overlapping equipment within the same reasonable useful lifetime (RUL) or rental period. | E15: • Patient already has a wheelchair on file within the reasonable useful lifetime, and a new wheelchair is billed → denied as same/similar equipment. • CPAP device billed while another supplier is still in active rental period → denied due to existing equipment rental. • Replacement hospital bed billed before the 5-year reasonable useful lifetime expired without medical justification → denial issued. • Oxygen equipment billed by a new provider when patient is still under capped rental with another supplier → denied. • Orthotic brace billed when a similar brace was previously provided recently → payer denies as duplicate equipment. | F15: • Eligibility verification for prior equipment ownership or rental status was not performed before billing. • Patient transferred from another supplier but prior equipment rental period still active. • Replacement equipment billed without documentation of medical necessity, damage, or change in condition. • Incorrect HCPCS coding causing payer to classify equipment as same/similar. • Lack of coordination between providers regarding existing DME history. • Missing documentation supporting replacement due to loss, theft, or irreparable damage. | G15: • Verify patient DME history through payer portal, Medicare IVR, or documentation from prior supplier. • Confirm whether the patient owns equipment or is still in rental period with another provider. • If replacement is medically necessary → submit documentation supporting change in condition, damage, or non-functionality. • Obtain and submit physician order and medical necessity records supporting need for different equipment. • If patient changed suppliers during rental period → coordinate billing transfer according to payer rules. • Appeal with documentation showing equipment is not same/similar (different HCPCS, upgraded need, or medical change). | I15: <tr data-carc="CO 97" data-type="co" data-rarc="M3 — Equipment is the same or similar to equipment already being used." data-denial="The claim was denied because the payer determined that the Durable Medical Equipment (DME) being billed is the same as, or similar to, equipment the patient already owns or is currently renting. Coverage is not allowed for duplicate or overlapping equipment within the same reasonable useful lifetime (RUL) or rental period." data-root="• Eligibility verification for prior equipment ownership or rental status was not performed before billing.\n• Patient transferred from another supplier but prior equipment rental period still active.\n• Replacement equipment billed without documentation of medical necessity, damage, or change in condition.\n• Incorrect HCPCS coding causing payer to classify equipment as same/similar.\n• Lack of coordination between providers regarding existing DME history.\n• Missing documentation supporting replacement due to loss, theft, or irreparable damage."><td><div class="row-num">#95</div><span class="carc-badge co">CO 97</span></td><td><span class="denial-reason">Bundling</span></td><td class="rarc-wrap"><div class="rarc-id">M3</div><div class="rarc-desc">Equipment is the same or similar to equipment already being used.</div></td><td class="td-meaning">The claim was denied because the payer determined that the Durable Medical Equipment (DME) being billed is the same as, or similar to, equipment the patient already owns or is currently renting. Coverage is not allowed for duplicate or overlapping equipment within the same reasonable useful lifetime (RUL) or rental period.</td><td><div class="chip-row"><span class="chip chip-green">Patient already has a wheelchair on file within the reasonable useful lifetime, and a new wheelchair is billed → denied as same/similar equipment.</span><span class="chip chip-green">CPAP device billed while another supplier is still in active rental period → denied due to existing equipment rental.</span><span class="chip chip-green">Replacement hospital bed billed before the 5-year reasonable useful lifetime expired without medical justification → denial issued.</span><span class="chip chip-green">Oxygen equipment billed by a new provider when patient is still under capped rental with another supplier → denied.</span><span class="chip chip-green">Orthotic brace billed when a similar brace was previously provided recently → payer denies as duplicate equipment.</span></div></td><td><div class="chip-row"><span class="chip chip-green">Eligibility verification for prior equipment ownership or rental status was not performed before billing.</span><span class="chip chip-green">Patient transferred from another supplier but prior equipment rental period still active.</span><span class="chip chip-green">Replacement equipment billed without documentation of medical necessity, damage, or change in condition.</span><span class="chip chip-green">Incorrect HCPCS coding causing payer to classify equipment as same/similar.</span><span class="chip chip-green">Lack of coordination between providers regarding existing DME history.</span><span class="chip chip-green">Missing documentation supporting replacement due to loss, theft, or irreparable damage.</span></div></td><td class="td-res">• Verify patient DME history through payer portal, Medicare IVR, or documentation from prior supplier.<br>• Confirm whether the patient owns equipment or is still in rental period with another provider.<br>• If replacement is medically necessary → submit documentation supporting change in condition, damage, or non-functionality.<br>• Obtain and submit physician order and medical necessity records supporting need for different equipment.<br>• If patient changed suppliers during rental period → coordinate billing transfer according to payer rules.<br>• Appeal with documentation showing equipment is not same/similar (different HCPCS, upgraded need, or medical change).</td></tr>
A16: CO 97 | B16: Bundling | C16: M86—Service denied because payment already made for same/similar procedure within a set time frame | D16: The claim was denied because the payer previously paid for the same or a similar procedure for the patient within a defined time limit or frequency period, and the current service falls within that restriction window. Payers enforce frequency edits to prevent duplicate or unnecessary services within short intervals unless medical necessity supports repetition. | E16: • Screening test billed again before allowed frequency interval expired → denied. • Procedure repeated within global period without modifier indicating separate service → denial issued. • Diagnostic imaging repeated within short timeframe without medical necessity → denied. • DME replacement billed before reasonable useful lifetime expired → denial applied. • Follow-up service submitted too soon after initial treatment → payer denies as duplicate timeframe service. | F16: • Service repeated within payer frequency limitation period. • Failure to verify prior claim history before billing. • Missing modifier indicating repeat procedure (e.g., -76, -77, -59) when appropriate. • Documentation lacking medical necessity for repeated service. • System or workflow issues causing duplicate submissions. • Staff unaware of payer frequency rules or global periods. | G16: • Review prior claim history to identify previously paid service and dates. • Determine whether repeat service was medically necessary and distinct. • If appropriate → resubmit or appeal with supporting documentation and correct modifier. • If duplicate billing occurred → correct or cancel claim as needed. • Verify global period rules if procedure-related. • Adjust account if denial is valid under frequency limitations. | I16: <tr data-carc="CO 97" data-type="co" data-rarc="M86 — Service denied because payment already made for same/similar procedure within set time frame." data-denial="The claim was denied because the payer previously paid for the same or a similar procedure for the patient within a defined time limit or frequency period, and the current service falls within that restriction window. Payers enforce frequency edits to prevent duplicate or unnecessary services within short intervals unless medical necessity supports repetition." data-root="• Service repeated within payer frequency limitation period.\n• Failure to verify prior claim history before billing.\n• Missing modifier indicating repeat procedure (e.g., -76, -77, -59) when appropriate.\n• Documentation lacking medical necessity for repeated service.\n• System or workflow issues causing duplicate submissions.\n• Staff unaware of payer frequency rules or global periods."><td><div class="row-num">#131</div><span class="carc-badge co">CO 97</span></td><td><span class="denial-reason">Bundling</span></td><td class="rarc-wrap"><div class="rarc-id">M86</div><div class="rarc-desc">Service denied because payment already made for same/similar procedure within set time frame.</div></td><td class="td-meaning">The claim was denied because the payer previously paid for the same or a similar procedure for the patient within a defined time limit or frequency period, and the current service falls within that restriction window. Payers enforce frequency edits to prevent duplicate or unnecessary services within short intervals unless medical necessity supports repetition.</td><td><div class="chip-row"><span class="chip chip-green">Screening test billed again before allowed frequency interval expired → denied.</span><span class="chip chip-green">Procedure repeated within global period without modifier indicating separate service → denial issued.</span><span class="chip chip-green">Diagnostic imaging repeated within short timeframe without medical necessity → denied.</span><span class="chip chip-green">DME replacement billed before reasonable useful lifetime expired → denial applied.</span><span class="chip chip-green">Follow-up service submitted too soon after initial treatment → payer denies as duplicate timeframe service.</span></div></td><td><div class="chip-row"><span class="chip chip-green">Service repeated within payer frequency limitation period.</span><span class="chip chip-green">Failure to verify prior claim history before billing.</span><span class="chip chip-green">Missing modifier indicating repeat procedure (e.g., -76, -77, -59) when appropriate.</span><span class="chip chip-green">Documentation lacking medical necessity for repeated service.</span><span class="chip chip-green">System or workflow issues causing duplicate submissions.</span><span class="chip chip-green">Staff unaware of payer frequency rules or global periods.</span></div></td><td class="td-res">• Review prior claim history to identify previously paid service and dates.<br>• Determine whether repeat service was medically necessary and distinct.<br>• If appropriate → resubmit or appeal with supporting documentation and correct modifier.<br>• If duplicate billing occurred → correct or cancel claim as needed.<br>• Verify global period rules if procedure-related.<br>• Adjust account if denial is valid under frequency limitations.</td></tr>
A17: CO 97 | B17: Bundling | C17: M80—Not covered when performed during the same session/date as a previously processed service for the patient | D17: The claim was denied because the service was performed on the same date or during the same session as another service that was already processed for the patient, and payer policy considers the additional service duplicate, inclusive, or not separately payable. When services overlap or are bundled under coding guidelines (such as NCCI edits), the payer will not issue additional payment. | E17: • Procedure billed twice on the same date for the same patient without modifier indicating distinct service → denied. • Office visit billed on same day as procedure where visit is considered included in procedure payment → denial issued. • Diagnostic test repeated same day without medical necessity documentation → denied as duplicate. • Multiple therapy services billed same session without appropriate modifiers → denial applied. • Provider submits same CPT code again after initial claim processed → payer treats as duplicate service. | F17: • Duplicate billing for same service or session. • Failure to apply appropriate modifiers (e.g., -59, -25, -76, -77) when services are distinct. • Services bundled under payer coding edits or NCCI rules. • Lack of awareness of same-day billing limitations. • System or workflow issues causing duplicate claim submission. • Documentation not supporting medical necessity for repeated services. | G17: • Review previously processed claim to identify overlapping service. Determine whether services were truly distinct and separately billable. • If appropriate → submit corrected claim with proper modifier and documentation. • If duplicate billing occurred → correct or void duplicate claim. • Appeal denial with medical necessity documentation if services were separate encounters. • Adjust account if denial is valid per bundling rules. | I17: <tr data-carc="CO 97" data-type="co" data-rarc="M80 — Not covered when performed during the same session/date as a previously processed service for the patient." data-denial="The claim was denied because the service was performed on the same date or during the same session as another service that was already processed for the patient, and payer policy considers the additional service duplicate, inclusive, or not separately payable. When services overlap or are bundled under coding guidelines (such as NCCI edits), the payer will not issue additional payment." data-root="• Duplicate billing for same service or session.\n• Failure to apply appropriate modifiers (e.g., -59, -25, -76, -77) when services are distinct.\n• Services bundled under payer coding edits or NCCI rules.\n• Lack of awareness of same-day billing limitations.\n• System or workflow issues causing duplicate claim submission.\n• Documentation not supporting medical necessity for repeated services."><td><div class="row-num">#126</div><span class="carc-badge co">CO 97</span></td><td><span class="denial-reason">Bundling</span></td><td class="rarc-wrap"><div class="rarc-id">M80</div><div class="rarc-desc">Not covered when performed during the same session/date as a previously processed service for the patient.</div></td><td class="td-meaning">The claim was denied because the service was performed on the same date or during the same session as another service that was already processed for the patient, and payer policy considers the additional service duplicate, inclusive, or not separately payable. When services overlap or are bundled under coding guidelines (such as NCCI edits), the payer will not issue additional payment.</td><td><div class="chip-row"><span class="chip chip-green">Procedure billed twice on the same date for the same patient without modifier indicating distinct service → denied.</span><span class="chip chip-green">Office visit billed on same day as procedure where visit is considered included in procedure payment → denial issued.</span><span class="chip chip-green">Diagnostic test repeated same day without medical necessity documentation → denied as duplicate.</span><span class="chip chip-green">Multiple therapy services billed same session without appropriate modifiers → denial applied.</span><span class="chip chip-green">Provider submits same CPT code again after initial claim processed → payer treats as duplicate service.</span></div></td><td><div class="chip-row"><span class="chip chip-green">Duplicate billing for same service or session.</span><span class="chip chip-green">Failure to apply appropriate modifiers (e.g., -59, -25, -76, -77) when services are distinct.</span><span class="chip chip-green">Services bundled under payer coding edits or NCCI rules.</span><span class="chip chip-green">Lack of awareness of same-day billing limitations.</span><span class="chip chip-green">System or workflow issues causing duplicate claim submission.</span><span class="chip chip-green">Documentation not supporting medical necessity for repeated services.</span></div></td><td class="td-res">• Review previously processed claim to identify overlapping service.<br>Determine whether services were truly distinct and separately billable.<br>• If appropriate → submit corrected claim with proper modifier and documentation.<br>• If duplicate billing occurred → correct or void duplicate claim.<br>• Appeal denial with medical necessity documentation if services were separate encounters.<br>• Adjust account if denial is valid per bundling rules.</td></tr>
A18: CO 97 | B18: Bundling | C18: M144—Payment for pre/post-operative care is included in the payment for the surgery/procedure and is not paid separately | D18: The claim was denied or adjusted because payment for pre-operative and/or post-operative care (e.g., E/M visits, consultations, or related services) is bundled into the global surgical allowance for the primary surgery/procedure. Separate billing is not allowed during the global period (typically 0, 10, or 90 days per CPT). | E18: • E/M visit day before surgery denied – bundled into surgical global fee. • Post-op follow-up visit within 90-day global period billed separately → denied. • Pre-op consultation or post-op complication management denied – included in surgery allowance. | F18: • Pre-/post-op service billed separately during global surgical period. • No exception modifier (e.g., -24, -79) used for unrelated E/M during global. • Provider unaware of global surgery package rules (0/10/90-day periods). • Billing software did not flag global period bundling. | G18: • Check global period for surgery code (0, 10, or 90 days) using CPT book or payer tool. • If service unrelated → add appropriate modifier (-24 unrelated E/M, -79 unrelated procedure) and resubmit (frequency 7). • If related → accept bundling and write off separate E/M charge. • Appeal with documentation proving unrelated service if modifier justified. | I18: <tr data-carc="CO 97" data-type="co" data-rarc="M144 — Pre-/post-operative care payment is included in the allowance for the surgery/procedure." data-denial="The claim was denied or adjusted because payment for pre-operative and/or post-operative care (e.g., E/M visits, consultations, or related services) is bundled into the global surgical allowance for the primary surgery/procedure. Separate billing is not allowed during the global period (typically 0, 10, or 90 days per CPT)." data-root="• Pre-/post-op service billed separately during global surgical period.\n• No exception modifier (e.g., -24, -79) used for unrelated E/M during global.\n• Provider unaware of global surgery package rules (0/10/90-day periods).\n• Billing software did not flag global period bundling."><td><div class="row-num">#81</div><span class="carc-badge co">CO 97</span></td><td><span class="denial-reason">Bundling</span></td><td class="rarc-wrap"><div class="rarc-id">M144</div><div class="rarc-desc">Pre-/post-operative care payment is included in the allowance for the surgery/procedure.</div></td><td class="td-meaning">The claim was denied or adjusted because payment for pre-operative and/or post-operative care (e.g., E/M visits, consultations, or related services) is bundled into the global surgical allowance for the primary surgery/procedure. Separate billing is not allowed during the global period (typically 0, 10, or 90 days per CPT).</td><td><div class="chip-row"><span class="chip chip-green">E/M visit day before surgery denied – bundled into surgical global fee.</span><span class="chip chip-green">Post-op follow-up visit within 90-day global period billed separately → denied.</span><span class="chip chip-green">Pre-op consultation or post-op complication management denied – included in surgery allowance.</span></div></td><td><div class="chip-row"><span class="chip chip-green">Pre-/post-op service billed separately during global surgical period.</span><span class="chip chip-green">No exception modifier (e.g., -24, -79) used for unrelated E/M during global.</span><span class="chip chip-green">Provider unaware of global surgery package rules (0/10/90-day periods).</span><span class="chip chip-green">Billing software did not flag global period bundling.</span></div></td><td class="td-res">• Check global period for surgery code (0, 10, or 90 days) using CPT book or payer tool.<br>• If service unrelated → add appropriate modifier (-24 unrelated E/M, -79 unrelated procedure) and resubmit (frequency 7).<br>• If related → accept bundling and write off separate E/M charge.<br>• Appeal with documentation proving unrelated service if modifier justified.</td></tr>
A19: CO 97 | B19: Bundling | C19: M15—Separately billed services/tests have been bundled as they are considered components of the same procedure | D19: The claim was denied or adjusted because separately billed services/tests were bundled into the primary procedure code as components of the same service. Separate payment is not allowed per NCCI edits, CPT guidelines, or payer policy (unbundling prohibition). | E19: • E/M visit billed with minor procedure on same day → E/M bundled into procedure. • Lab test or imaging billed separately when considered part of main procedure (e.g., intra-operative monitoring). • Injection or supply billed apart from surgical code that includes it. | F19: • Unbundling: Billing component services separately instead of using comprehensive code. • Missing or incorrect modifier (e.g., -59/-XU not used or not justified). • Provider unaware of NCCI edits or payer bundling rules. • Billing software did not flag bundled services. | G19: • Review NCCI edits and payer policy for the billed codes to confirm bundling. • If modifier appropriate (e.g., -59 for distinct service) → add correct modifier and resubmit (frequency 7). • If truly bundled → accept adjustment and post write-off. • Appeal with documentation (op notes, progress notes) proving distinct service if justified. | I19: <tr data-carc="CO 97" data-type="co" data-rarc="M15 — Separately billed services/tests have been bundled as they are considered components of the same procedure. Separate payment is not allowed." data-denial="The claim was denied or adjusted because separately billed services/tests were bundled into the primary procedure code as components of the same service. Separate payment is not allowed per NCCI edits, CPT guidelines, or payer policy (unbundling prohibition)." data-root="• Unbundling: Billing component services separately instead of using comprehensive code.\n• Missing or incorrect modifier (e.g., -59/-XU not used or not justified).\n• Provider unaware of NCCI edits or payer bundling rules.\n• Billing software did not flag bundled services."><td><div class="row-num">#39</div><span class="carc-badge co">CO 97</span></td><td><span class="denial-reason">Bundling</span></td><td class="rarc-wrap"><div class="rarc-id">M15</div><div class="rarc-desc">Separately billed services/tests have been bundled as they are considered components of the same procedure. Separate payment is not allowed.</div></td><td class="td-meaning">The claim was denied or adjusted because separately billed services/tests were bundled into the primary procedure code as components of the same service. Separate payment is not allowed per NCCI edits, CPT guidelines, or payer policy (unbundling prohibition).</td><td><div class="chip-row"><span class="chip chip-green">E/M visit billed with minor procedure on same day → E/M bundled into procedure.</span><span class="chip chip-green">Lab test or imaging billed separately when considered part of main procedure (e.g., intra-operative monitoring).</span><span class="chip chip-green">Injection or supply billed apart from surgical code that includes it.</span></div></td><td><div class="chip-row"><span class="chip chip-green">Unbundling: Billing component services separately instead of using comprehensive code.</span><span class="chip chip-green">Missing or incorrect modifier (e.g., -59/-XU not used or not justified).</span><span class="chip chip-green">Provider unaware of NCCI edits or payer bundling rules.</span><span class="chip chip-green">Billing software did not flag bundled services.</span></div></td><td class="td-res">• Review NCCI edits and payer policy for the billed codes to confirm bundling.<br>• If modifier appropriate (e.g., -59 for distinct service) → add correct modifier and resubmit (frequency 7).<br>• If truly bundled → accept adjustment and post write-off.<br>• Appeal with documentation (op notes, progress notes) proving distinct service if justified.</td></tr>
... A30: CO 27 | B30: Claim Spans Both Eligible and Ineligible Coverage Periods | C30: N273—Claim spans eligible and ineligible periods of coverage | D30: The claim was denied or partially processed because the dates of service on the claim span both eligible and ineligible periods of the patient’s insurance coverage. This means that part of the service period falls outside the patient’s active coverage window, making those portions non-payable. Payers require claims to align strictly with coverage eligibility dates. If a claim includes dates before coverage began or after it ended, the payer may deny the entire claim or only process the eligible portion, depending on policy. | E30: Hospital stay spans coverage start date → early dates denied, later dates paid. Therapy services billed across eligibility termination → post-termination dates denied. Claim includes dates before insurance effective date → denial applied. Coverage ended mid-treatment → claim partially processed. Incorrect service span submitted → entire claim rejected. | F30: Service dates extend beyond coverage eligibility period. Failure to verify eligibility for entire date range. Incorrect service span entered on claim. Coverage start/end dates not aligned with billing. Staff unaware of partial eligibility rules. System or billing errors in date handling. | G30: Verify patient eligibility dates with payer. Split claim into eligible and ineligible service periods if required. Bill only for dates within active coverage. Bill patient or secondary payer for non-covered dates. Resubmit corrected claim with appropriate service span. Appeal if denial occurred despite valid coverage. | I30: <tr data-carc="" data-type="" data-rarc="N273 — Missing/incomplete/invalid other payer operating provider identifier." data-denial="" data-root=""><td><div class="row-num">#401</div><span class="carc-badge "></span></td><td><span class="denial-reason"></span></td><td class="rarc-wrap"><div class="rarc-id">N273</div><div class="rarc-desc">Missing/incomplete/invalid other payer operating provider identifier.</div></td><td class="td-meaning"></td><td><div class="chip-row"></div></td><td><div class="chip-row"></div></td><td class="td-res"></td></tr>
A31: CO 109 | B31: Claim Submitted for Patient Enrolled in Medicare Advantage Plan | C31: MA86—Alert: A claim has been received for a beneficiary enrolled in a Medicare Advantage plan | D31: This alert indicates that the beneficiary is enrolled in a Medicare Advantage (Part C) plan, and therefore claims should be submitted to the Medicare Advantage plan rather than traditional Medicare (Fee-for-Service). | E31: Claim submitted to traditional Medicare for patient enrolled in Medicare Advantage → denied. Patient switched to Medicare Advantage but system still shows Medicare FFS → incorrect billing. Provider unaware of patient’s MA enrollment → claim rejected. Medicare Advantage plan requires authorization but not obtained → denial applied. Dual eligibility confusion leads to incorrect payer submission → claim impacted. | F31: Failure to verify current insurance coverage. Outdated patient insurance information in system. Incorrect assumption that Medicare is primary payer. Lack of awareness of Medicare Advantage enrollment. COB or eligibility verification not performed. | G31: Verify patient’s current insurance and confirm Medicare Advantage enrollment. Identify correct Medicare Advantage plan and payer ID. Submit claim to the appropriate Medicare Advantage payer. Obtain authorization if required by the plan. Resubmit corrected claim. Follow up on claim processing with MA plan.
A32: CO 109 | B32: Claim Submitted to Incorrect Payer | C32: N103 | N104—This claim/service is not payable under this payer/contractor. Submit the claim to the correct payer | D32: The claim or service was denied because it was submitted to a payer that is not responsible for payment. | E32: Claim submitted to commercial payer but patient has Medicare Advantage → denied. Workers’ compensation case billed to regular health insurance → rejected. Secondary payer billed without primary payer adjudication → denial issued. Patient has updated insurance but old payer billed → claim denied. COB indicates another payer is primary → incorrect submission. | F32: Incorrect payer selection during claim submission. Failure to verify current insurance coverage. Outdated patient insurance information. Incorrect coordination of benefits (COB). Lack of awareness of special payer types (WC, liability, MA plans). System or registration errors. | G32: Verify patient’s current insurance coverage and payer responsibility. Identify correct primary/secondary payer. Update claim with accurate payer information. Submit claim to the correct payer. Include primary payer EOB if billing secondary. Follow up to ensure proper claim processing.
A33: CO 16 | B33: Claim/Service Split and Processed as Part of Combined Claim | C33: MA15—Alert: Separately billed claim/service was processed as part of a combined claim. Expect another notice for the remaining services. | D33: This alert indicates that the submitted claim or service line was separated and processed as part of a combined claim, typically to facilitate more efficient adjudication. The payer has processed a portion of the services and will issue a separate remittance notice for the remaining services. | E33: Multi-line claim submitted → payer processes some lines separately → multiple remittances issued. Claim includes services with different processing rules (e.g., professional vs technical) → split occurs. High-volume claim divided for faster adjudication → partial payment received first. Services requiring additional review processed separately → secondary notice follows. System-driven claim splitting by payer → multiple EOBs generated. | F33: Payer internal processing rules for claim splitting. Mixed service types within a single claim. Services requiring different adjudication workflows. High-volume or complex claims. System-based claim segmentation by payer. | G33: Review remittance advice for processed service lines. Track claim using claim number and service dates. Wait for additional remittance for remaining services. Reconcile all payments once all notices are received. Follow up with payer if remaining services are not processed timely.
A34: CO 16 | B34: CLIA Missing | C34: M91—Missing/incomplete/invalid provider specialty/taxonomy | D34: The claim was denied because laboratory services performed under different CLIA (Clinical Laboratory Improvement Amendments) certification numbers were billed on the same claim. Payer policy requires that services associated with each CLIA number be submitted on separate claims, since each CLIA certificate represents a distinct laboratory entity with its own regulatory identification. | E34: • Multiple lab tests performed by different laboratory locations with separate CLIA numbers billed together → denied. • Reference lab services combined with in-house lab services on one claim → payer rejects claim. • Hospital outreach lab and physician office lab services submitted under single claim despite different CLIA IDs → denial issued. • Point-of-care testing and external lab testing billed together → denial applied. • Billing system populated only one CLIA number for multiple lab providers → claim denied. | F34: • Multiple CLIA-certified entities included on one claim submission. • Failure to split services by performing laboratory. • Billing system limitations allowing only one CLIA number per claim. • Staff unaware of CLIA billing requirements. • Incorrect claim setup when reference labs are involved. • Interface or mapping errors between lab system and billing system. | G34: • Identify which services correspond to each CLIA certification number. • Split the claim into separate claims — one per CLIA number. • Ensure correct CLIA number is reported in the appropriate claim field for each submission. • Verify rendering or performing provider information aligns with CLIA entity. • Resubmit corrected claims individually. • Appeal if denial occurred despite correct separation. | I34: <tr data-carc="CO 16" data-type="co" data-rarc="M91 — Lab procedures with different CLIA certification numbers must be billed on separate claims." data-denial="The claim was denied because laboratory services performed under different CLIA (Clinical Laboratory Improvement Amendments) certification numbers were billed on the same claim. Payer policy requires that services associated with each CLIA number be submitted on separate claims, since each CLIA certificate represents a distinct laboratory entity with its own regulatory identification." data-root="• Multiple CLIA-certified entities included on one claim submission.\n• Failure to split services by performing laboratory.\n• Billing system limitations allowing only one CLIA number per claim.\n• Staff unaware of CLIA billing requirements.\n• Incorrect claim setup when reference labs are involved.\n• Interface or mapping errors between lab system and billing system."><td><div class="row-num">#134</div><span class="carc-badge co">CO 16</span></td><td><span class="denial-reason">CLIA Missing</span></td><td class="rarc-wrap"><div class="rarc-id">M91</div><div class="rarc-desc">Lab procedures with different CLIA certification numbers must be billed on separate claims.</div></td><td class="td-meaning">The claim was denied because laboratory services performed under different CLIA (Clinical Laboratory Improvement Amendments) certification numbers were billed on the same claim. Payer policy requires that services associated with each CLIA number be submitted on separate claims, since each CLIA certificate represents a distinct laboratory entity with its own regulatory identification.</td><td><div class="chip-row"><span class="chip chip-green">Multiple lab tests performed by different laboratory locations with separate CLIA numbers billed together → denied.</span><span class="chip chip-green">Reference lab services combined with in-house lab services on one claim → payer rejects claim.</span><span class="chip chip-green">Hospital outreach lab and physician office lab services submitted under single claim despite different CLIA IDs → denial issued.</span><span class="chip chip-green">Point-of-care testing and external lab testing billed together → denial applied.</span><span class="chip chip-green">Billing system populated only one CLIA number for multiple lab providers → claim denied.</span></div></td><td><div class="chip-row"><span class="chip chip-green">Multiple CLIA-certified entities included on one claim submission.</span><span class="chip chip-green">Failure to split services by performing laboratory.</span><span class="chip chip-green">Billing system limitations allowing only one CLIA number per claim.</span><span class="chip chip-green">Staff unaware of CLIA billing requirements.</span><span class="chip chip-green">Incorrect claim setup when reference labs are involved.</span><span class="chip chip-green">Interface or mapping errors between lab system and billing system.</span></div></td><td class="td-res">• Identify which services correspond to each CLIA certification number.<br>• Split the claim into separate claims — one per CLIA number.<br>• Ensure correct CLIA number is reported in the appropriate claim field for each submission.<br>• Verify rendering or performing provider information aligns with CLIA entity.<br>• Resubmit corrected claims individually.<br>• Appeal if denial occurred despite correct separation.</td></tr>
A35: CO 16 | B35: CLIA Missing | C35: MA120 — Missing/incomplete/invalid CLIA certification number. | D35: The claim was denied because the required CLIA (Clinical Laboratory Improvement Amendments) certification number was missing, incomplete, invalid, or not recognized by the payer. On the CMS-1500 claim form, the CLIA number is reported in Box 23 — Prior Authorization Number, specifically in the designated CLIA field when applicable, along with service facility information in Box 32 if the performing lab differs from the billing provider. On the UB-04 claim form, the CLIA number is typically reported in Form Locator (FL) 63 — Treatment Authorization Code or in remarks/associated provider certification records depending on payer instructions, with laboratory services reflected through FL 42 — Revenue Code and FL 44 — HCPCS/Rate/HIPPS Code. | E35: • Laboratory service billed without CLIA number → denied. • Incorrect or expired CLIA certification number entered → rejection issued. • Billing provider CLIA used instead of performing lab CLIA → denial applied. • System transmission error dropped CLIA number → payer rejects claim. • CLIA-waived test billed without appropriate certification number → claim denied. | F35: • CLIA field not populated during claim creation. • Expired or invalid CLIA certification. • Mismatch between performing lab and billing provider CLIA. • Staff unaware of CLIA reporting requirements. • System mapping or clearinghouse errors. • Enrollment records not updated. | G35: • Verify correct CLIA certification number for performing laboratory. • Confirm certification is active for the date of service. • Correct claim with accurate CLIA number in appropriate field. • Ensure performing provider information aligns with CLIA records. • Resubmit corrected claim. • Appeal if denial applied incorrectly with supporting documentation. | I35: <tr data-carc="CO 16" data-type="co" data-rarc="MA120 — Missing/incomplete/invalid CLIA certification number." data-denial="The claim was denied because the required CLIA (Clinical Laboratory Improvement Amendments) certification number was missing, incomplete, invalid, or not recognized by the payer. On the CMS-1500 claim form, the CLIA number is reported in Box 23 — Prior Authorization Number, specifically in the designated CLIA field when applicable, along with service facility information in Box 32 if the performing lab differs from the billing provider. On the UB-04 claim form, the CLIA number is typically reported in Form Locator (FL) 63 — Treatment Authorization Code or in remarks/associated provider certification records depending on payer instructions, with laboratory services reflected through FL 42 — Revenue Code and FL 44 — HCPCS/Rate/HIPPS Code." data-root="• CLIA field not populated during claim creation.\n• Expired or invalid CLIA certification.\n• Mismatch between performing lab and billing provider CLIA.\n• Staff unaware of CLIA reporting requirements.\n• System mapping or clearinghouse errors.\n• Enrollment records not updated."><td><div class="row-num">#152</div><span class="carc-badge co">CO 16</span></td><td><span class="denial-reason">CLIA Missing</span></td><td class="rarc-wrap"><div class="rarc-id">MA120</div><div class="rarc-desc">Missing/incomplete/invalid CLIA certification number.</div></td><td class="td-meaning">The claim was denied because the required CLIA (Clinical Laboratory Improvement Amendments) certification number was missing, incomplete, invalid, or not recognized by the payer. On the CMS-1500 claim form, the CLIA number is reported in Box 23 — Prior Authorization Number, specifically in the designated CLIA field when applicable, along with service facility information in Box 32 if the performing lab differs from the billing provider. On the UB-04 claim form, the CLIA number is typically reported in Form Locator (FL) 63 — Treatment Authorization Code or in remarks/associated provider certification records depending on payer instructions, with laboratory services reflected through FL 42 — Revenue Code and FL 44 — HCPCS/Rate/HIPPS Code.</td><td><div class="chip-row"><span class="chip chip-green">Laboratory service billed without CLIA number → denied.</span><span class="chip chip-green">Incorrect or expired CLIA certification number entered → rejection issued.</span><span class="chip chip-green">Billing provider CLIA used instead of performing lab CLIA → denial applied.</span><span class="chip chip-green">System transmission error dropped CLIA number → payer rejects claim.</span><span class="chip chip-green">CLIA-waived test billed without appropriate certification number → claim denied.</span></div></td><td><div class="chip-row"><span class="chip chip-green">CLIA field not populated during claim creation.</span><span class="chip chip-green">Expired or invalid CLIA certification.</span><span class="chip chip-green">Mismatch between performing lab and billing provider CLIA.</span><span class="chip chip-green">Staff unaware of CLIA reporting requirements.</span><span class="chip chip-green">System mapping or clearinghouse errors.</span><span class="chip chip-green">Enrollment records not updated.</span></div></td><td class="td-res">• Verify correct CLIA certification number for performing laboratory.<br>• Confirm certification is active for the date of service.<br>• Correct claim with accurate CLIA number in appropriate field.<br>• Ensure performing provider information aligns with CLIA records.<br>• Resubmit corrected claim.<br>• Appeal if denial applied incorrectly with supporting documentation.</td></tr>
A36: CO 97 | B36: Component of Basic Benefit Paid as Covered Service | C36: N156—Alert: A component of the basic benefit has been paid as a covered service | D36: This alert indicates that a portion (component) of the billed service has been recognized and paid under the patient’s basic benefit coverage, rather than being processed separately as an independent service. | E36: Minor procedure billed separately but included in major procedure payment → not paid separately. Supplies or services included in global surgical package → bundled into primary service. Diagnostic component included in comprehensive service → no separate reimbursement. Routine services included in base benefit → adjusted accordingly. Multiple related services billed → payer pays only primary service and bundles others. | F36: Bundling rules under payer policy. Services considered integral to primary procedure. Global payment packages (e.g., surgery, maternity). Incorrect unbundling of services during billing. Lack of awareness of included components. | G36: Review remittance advice to identify bundled components. Verify payer bundling rules and coding guidelines. Ensure correct coding and modifier usage (if applicable). Accept adjustment if bundling is appropriate. Appeal if services are distinct and should be separately payable. | I36: <tr data-carc="" data-type="" data-rarc="N156 — Alert: The patient is responsible for the difference between the approved treatment and the elective treatment." data-denial="" data-root=""><td><div class="row-num">#282</div><span class="carc-badge "></span></td><td><span class="denial-reason"></span></td><td class="rarc-wrap"><div class="rarc-id">N156</div><div class="rarc-desc">Alert: The patient is responsible for the difference between the approved treatment and the elective treatment.</div></td><td class="td-meaning"></td><td><div class="chip-row"></div></td><td><div class="chip-row"></div></td><td class="td-res"></td></tr>
A37: CO 201 | B37: Conditional Payment Due to Emergency Services | C37: N116—Alert: This payment is being made conditionally because the service was provided in an emergency setting | D37: This alert indicates that the payment is being made conditionally because the service was provided in an emergency setting. On the CMS-1500 claim form, emergency services are indicated in Box 24C — Emergency Indicator, On the UB-04 claim form, emergency services are identified using Form Locator (FL) 14 — Type of Admission (Emergency) and FL 15 — Source of Admission | E37: Emergency room visit paid conditionally pending liability insurance determination. Auto accident-related services paid temporarily while fault is under review. Workers’ compensation case not yet established → payer issues conditional payment. Emergency care provided without confirmed primary payer → provisional payment made. Payer awaiting COB clarification but issues interim payment → subject to adjustment. | F37: Emergency services require immediate care regardless of coverage confirmation. Unclear primary payer responsibility at time of service. Pending liability, workers’ compensation, or third-party insurance review. Incomplete COB or accident-related information. Regulatory requirement to pay emergency services conditionally. | G37: Verify if another payer (liability, WC, auto insurance) is responsible. Monitor claim for future adjustments or recoupments. Provide additional information to payer if requested. Coordinate benefits once primary payer is identified. Refund or reconcile if overpayment is later identified. | I37: <tr data-carc="" data-type="" data-rarc="N116 — Alert: This payment is being made conditionally because the service was provided in the home, and it is possible that the patient is under a home health episode of care. When a patient is treated under a home health episode of care, consolidated billing requires that certain therapy services and supplies, such as this, be included in the home health agency's (HHA's) payment. This payment will need to be recouped from you if we establish that the patient is concurrently receiving treatment under an HHA episode of care." data-denial="" data-root=""><td><div class="row-num">#245</div><span class="carc-badge "></span></td><td><span class="denial-reason"></span></td><td class="rarc-wrap"><div class="rarc-id">N116</div><div class="rarc-desc">Alert: This payment is being made conditionally because the service was provided in the home, and it is possible that the patient is under a home health episode of care. When a patient is treated under a home health episode of care, consolidated billing requires that certain therapy services and supplies, such as this, be included in the home health agency's (HHA's) payment. This payment will need to be recouped from you if we establish that the patient is concurrently receiving treatment under an HHA episode of care.</div></td><td class="td-meaning"></td><td><div class="chip-row"></div></td><td><div class="chip-row"></div></td><td class="td-res"></td></tr>
A38: CO 45 | B38: Contractual Agreement Governs Billing | C38: N381—Alert: Consult the payer's published payment policies for this service/procedure | D38: This alert indicates that the billing, payment, or coverage determination for the service is governed by the provider’s contractual agreement with the payer. The payer is instructing the provider to review the contract terms for applicable restrictions, reimbursement methodology, bundling rules, or billing limitations that apply to the charges submitted. Service and billing details are reflected on the CMS-1500 Box 24D — Procedure Code, Box 24A — Date(s) of Service, and Box 29 — Amount Paid, or on the UB-04 Form Locator (FL) 44 — HCPCS/Rate/HIPPS Code, FL 42 — Revenue Code, and FL 54 — Prior Payments, which determine reimbursement calculations under the contract. | E38: Service included in contractually bundled payment → separate payment denied. Contract limits reimbursement for specific procedure category → payment reduced. Provider billing outside contracted rate schedule → adjustment applied. Service excluded from reimbursement under contract terms → denied. Contract specifies different payment methodology (per diem, case rate) → claim adjusted. | F38: Contractual bundling rules not recognized during billing. Provider unaware of negotiated reimbursement limitations. Incorrect expectation of fee schedule payment instead of contract rate. Billing system not aligned with payer contract terms. Misinterpretation of contract provisions. Outdated contract reference used during billing review. | G38: Review the provider-payer contract terms for the service billed. Verify reimbursement methodology and restrictions under the agreement. Confirm whether service is bundled, excluded, or subject to reduced rate. Correct billing if contract requires different coding or submission method. Appeal only if contract terms were misapplied by the payer. Coordinate with contracting department for clarification if needed. | I38: <tr data-carc="" data-type="" data-rarc="N381 — Alert: Consult our contractual agreement for restrictions/billing/payment information related to these charges." data-denial="" data-root=""><td><div class="row-num">#513</div><span class="carc-badge "></span></td><td><span class="denial-reason"></span></td><td class="rarc-wrap"><div class="rarc-id">N381</div><div class="rarc-desc">Alert: Consult our contractual agreement for restrictions/billing/payment information related to these charges.</div></td><td class="td-meaning"></td><td><div class="chip-row"></div></td><td><div class="chip-row"></div></td><td class="td-res"></td></tr>
A39: PR 3 | B39: Copay Amount | C39: PR (Patient Responsibility) | D39: A fixed flat fee the patient must pay for a specific covered service (e.g., $30 office visit copay), regardless of allowed amount. Payer pays the balance after copay. | E39: • $25 copay for primary care visit. • $50 ER copay applied to emergency service. • Tiered copays (e.g., $10 generic Rx vs. $50 specialist). • Copay waived incorrectly for preventive care but applied elsewhere. | F39: • Plan requires fixed copay per service type/visit. • Copay not collected at time of service. • Error in copay waiver verification (e.g., for preventive). Multiple visits/services triggering separate copays. | G39: • Check EOB for exact copay amount and service applied to. • Bill patient directly for PR-3 amount. • If waiver error, appeal with documentation (e.g., preventive service). • Pursue patient payment promptly. | I39: <tr data-carc="PR 3" data-type="pr" data-rarc="PR (Patient Responsibility)" data-denial="A fixed flat fee the patient must pay for a specific covered service (e.g., $30 office visit copay), regardless of allowed amount. Payer pays the balance after copay." data-root="• Plan requires fixed copay per service type/visit.\n• Copay not collected at time of service.\n• Error in copay waiver verification (e.g., for preventive).\nMultiple visits/services triggering separate copays."><td><div class="row-num">#4</div><span class="carc-badge pr">PR 3</span></td><td><span class="denial-reason">Copay Amount</span></td><td class="rarc-wrap"><div class="rarc-id">PR</div><div class="rarc-desc"></div></td><td class="td-meaning">A fixed flat fee the patient must pay for a specific covered service (e.g., $30 office visit copay), regardless of allowed amount. Payer pays the balance after copay.</td><td><div class="chip-row"><span class="chip chip-green">$25 copay for primary care visit.</span><span class="chip chip-green">$50 ER copay applied to emergency service.</span><span class="chip chip-green">Tiered copays (e.g., $10 generic Rx vs. $50 specialist).</span><span class="chip chip-green">Copay waived incorrectly for preventive care but applied elsewhere.</span></div></td><td><div class="chip-row"><span class="chip chip-green">Plan requires fixed copay per service type/visit.</span><span class="chip chip-green">Copay not collected at time of service.</span><span class="chip chip-green">Error in copay waiver verification (e.g., for preventive).</span><span class="chip chip-green">Multiple visits/services triggering separate copays.</span></div></td><td class="td-res">• Check EOB for exact copay amount and service applied to.<br>• Bill patient directly for PR-3 amount.<br>• If waiver error, appeal with documentation (e.g., preventive service).<br>• Pursue patient payment promptly.</td></tr>
A40: CO 22 | B40: Covered by Another Payer | C40: MA16 — The patient is covered by the Black Lung Program. Send this claim to the Department of Labor, Federal Black Lung Program, P.O. Box 828, Lanham-Seabrook MD 20703. | D40: The claim was denied because the patient is covered under the Federal Black Lung Program, administered by the U.S. Department of Labor (DOL). Services related to treatment of black lung disease (coal workers’ pneumoconiosis) must be billed directly to the Department of Labor rather than Medicare or another payer. On CMS-1500 Box 11 — Insured’s Policy Group Number and Box 9–9d — Other Insured Information, and on the UB-04 Form Locator (FL) 50–60 — Payer and Insured Information | E40: • Medicare billed for black lung-related treatment → denied with instruction to bill DOL. • Provider unaware patient had Black Lung coverage → claim rejected. • Respiratory treatment related to pneumoconiosis billed to primary insurer instead of DOL → denial applied. • Eligibility verification did not identify Federal Black Lung coverage → claim denied. • Dual coverage patient incorrectly billed under Medicare → payer rejects claim. | F40: • Incorrect primary payer selection. • Failure to verify Black Lung Program eligibility. • Registration did not capture DOL coverage details. • Staff unfamiliar with Black Lung billing requirements. • Coordination of benefits confusion. • Incomplete insurance documentation at intake. | G40: • Verify patient eligibility under the Federal Black Lung Program. • Confirm whether services are related to black lung condition. • Submit claim to the U.S. Department of Labor, Federal Black Lung Program. • Adjust original claim if submitted to incorrect payer. • Update patient insurance records to reflect correct primary payer. • Appeal only if services are unrelated to black lung and should be covered by another payer. | I40: <tr data-carc="" data-type="" data-rarc="MA16 — The patient is covered by the Black Lung Program. Send this claim to the Department of Labor, Federal Black Lung Program, P.O. Box 828, Lanham-Seabrook MD 20703." data-denial="" data-root=""><td><div class="row-num">#163</div><span class="carc-badge "></span></td><td><span class="denial-reason"></span></td><td class="rarc-wrap"><div class="rarc-id">MA16</div><div class="rarc-desc">The patient is covered by the Black Lung Program. Send this claim to the Department of Labor, Federal Black Lung Program, P.O. Box 828, Lanham-Seabrook MD 20703.</div></td><td class="td-meaning"></td><td><div class="chip-row"></div></td><td><div class="chip-row"></div></td><td class="td-res"></td></tr>
A41: CO 109 | B41: Covered by Another Payer | C41: M40—Claim must be assigned and must be filed by the practitioner's employer | D41: The claim was denied because the service must be billed by the practitioner’s employer or the entity that holds the billing rights (such as a group practice, facility, or organization), and the claim was submitted incorrectly by an individual provider or the wrong billing entity. | E41: • Employed physician submits claim under individual NPI instead of group/practice NPI → denied. • Provider working under a hospital or clinic employment contract bills services directly rather than through employer → denial issued. • Services performed in a facility setting requiring billing by facility entity but submitted by individual practitioner → denied. • Locum tenens or contract provider billing without proper reassignment enrollment → claim rejected/denied. • Incorrect billing provider information submitted (Type 1 vs Type 2 NPI mismatch) → payer requires employer submission. | F41: • Incorrect billing provider selected during claim submission. • Provider enrollment or reassignment of benefits not properly established with payer. • Lack of awareness that employed providers must bill under employer entity. • Credentialing or PECOS enrollment incomplete or outdated. • System configuration errors causing wrong billing NPI population. • Workflow gap between credentialing and billing departments. | G41: • Verify provider employment status and determine correct billing entity. • Confirm reassignment of benefits enrollment with payer (e.g., group enrollment active). • Correct claim with appropriate billing provider (employer/group NPI) and resubmit. • If enrollment missing → complete credentialing or reassignment process before rebilling. • Appeal if claim was denied incorrectly despite proper billing structure. • Review contracts to confirm billing responsibility when services involve multiple entities. | I41: <tr data-carc="CO 109" data-type="co" data-rarc="M40 — Claim must be assigned and must be filed by the practitioner's employer." data-denial="The claim was denied because the service must be billed by the practitioner’s employer or the entity that holds the billing rights (such as a group practice, facility, or organization), and the claim was submitted incorrectly by an individual provider or the wrong billing entity." data-root="• Incorrect billing provider selected during claim submission.\n• Provider enrollment or reassignment of benefits not properly established with payer.\n• Lack of awareness that employed providers must bill under employer entity.\n• Credentialing or PECOS enrollment incomplete or outdated.\n• System configuration errors causing wrong billing NPI population.\n• Workflow gap between credentialing and billing departments."><td><div class="row-num">#101</div><span class="carc-badge co">CO 109</span></td><td><span class="denial-reason">Covered by Another Payer</span></td><td class="rarc-wrap"><div class="rarc-id">M40</div><div class="rarc-desc">Claim must be assigned and must be filed by the practitioner's employer.</div></td><td class="td-meaning">The claim was denied because the service must be billed by the practitioner’s employer or the entity that holds the billing rights (such as a group practice, facility, or organization), and the claim was submitted incorrectly by an individual provider or the wrong billing entity.</td><td><div class="chip-row"><span class="chip chip-green">Employed physician submits claim under individual NPI instead of group/practice NPI → denied.</span><span class="chip chip-green">Provider working under a hospital or clinic employment contract bills services directly rather than through employer → denial issued.</span><span class="chip chip-green">Services performed in a facility setting requiring billing by facility entity but submitted by individual practitioner → denied.</span><span class="chip chip-green">Locum tenens or contract provider billing without proper reassignment enrollment → claim rejected/denied.</span><span class="chip chip-green">Incorrect billing provider information submitted (Type 1 vs Type 2 NPI mismatch) → payer requires employer submission.</span></div></td><td><div class="chip-row"><span class="chip chip-green">Incorrect billing provider selected during claim submission.</span><span class="chip chip-green">Provider enrollment or reassignment of benefits not properly established with payer.</span><span class="chip chip-green">Lack of awareness that employed providers must bill under employer entity.</span><span class="chip chip-green">Credentialing or PECOS enrollment incomplete or outdated.</span><span class="chip chip-green">System configuration errors causing wrong billing NPI population.</span><span class="chip chip-green">Workflow gap between credentialing and billing departments.</span></div></td><td class="td-res">• Verify provider employment status and determine correct billing entity.<br>• Confirm reassignment of benefits enrollment with payer (e.g., group enrollment active).<br>• Correct claim with appropriate billing provider (employer/group NPI) and resubmit.<br>• If enrollment missing → complete credentialing or reassignment process before rebilling.<br>• Appeal if claim was denied incorrectly despite proper billing structure.<br>• Review contracts to confirm billing responsibility when services involve multiple entities.</td></tr>
A42: CO 22 | B42: Covered by Another Payer | C42: N596 — Records reflect the injured party did not complete a Medical Authorization for this loss. | D42: The claim was denied or suspended because the payer (usually no-fault auto, liability, or workers' comp insurer) has no record of the injured patient signing a Medical Authorization/Release form (HIPAA-compliant release specific to the loss/accident). | E42: • No-fault/PIP auto claim denied – patient did not sign insurer's medical authorization form. • Liability (slip-and-fall) claim held – no signed release for medical records. • Workers' comp claim rejected because injured worker refused or forgot to sign authorization for claims adjuster. | F42: • Patient did not sign medical authorization/release form at intake or when requested. • Provider failed to collect or forward signed authorization to payer/insurer. • Injury not identified as accident-related at time of service → form not obtained. • Patient refused to sign (privacy concerns) or form lost/misfiled. | G42: • Confirm required form with payer (claims adjuster or portal). Obtain signed authorization from patient (payer-specific form or compliant HIPAA release for this loss). • Submit signed form to payer (fax/upload/mail) with claim reference. • Request reprocessing once form received. • If patient refuses → inform payer; may bill patient directly or write off. | I42: <tr data-carc="CO 22" data-type="co" data-rarc="N596 — Records reflect the injured party did not complete a Medical Authorization for this loss." data-denial="The claim was denied or suspended because the payer (usually no-fault auto, liability, or workers' comp insurer) has no record of the injured patient signing a Medical Authorization/Release form (HIPAA-compliant release specific to the loss/accident)." data-root="• Patient did not sign medical authorization/release form at intake or when requested.\n• Provider failed to collect or forward signed authorization to payer/insurer.\n• Injury not identified as accident-related at time of service → form not obtained.\n• Patient refused to sign (privacy concerns) or form lost/misfiled."><td><div class="row-num">#31</div><span class="carc-badge co">CO 22</span></td><td><span class="denial-reason">Covered by Another Payer</span></td><td class="rarc-wrap"><div class="rarc-id">N596</div><div class="rarc-desc">Records reflect the injured party did not complete a Medical Authorization for this loss.</div></td><td class="td-meaning">The claim was denied or suspended because the payer (usually no-fault auto, liability, or workers' comp insurer) has no record of the injured patient signing a Medical Authorization/Release form (HIPAA-compliant release specific to the loss/accident).</td><td><div class="chip-row"><span class="chip chip-green">No-fault/PIP auto claim denied – patient did not sign insurer's medical authorization form.</span><span class="chip chip-green">Liability (slip-and-fall) claim held – no signed release for medical records.</span><span class="chip chip-green">Workers' comp claim rejected because injured worker refused or forgot to sign authorization for claims adjuster.</span></div></td><td><div class="chip-row"><span class="chip chip-green">Patient did not sign medical authorization/release form at intake or when requested.</span><span class="chip chip-green">Provider failed to collect or forward signed authorization to payer/insurer.</span><span class="chip chip-green">Injury not identified as accident-related at time of service → form not obtained.</span><span class="chip chip-green">Patient refused to sign (privacy concerns) or form lost/misfiled.</span></div></td><td class="td-res">• Confirm required form with payer (claims adjuster or portal).<br>Obtain signed authorization from patient (payer-specific form or compliant HIPAA release for this loss).<br>• Submit signed form to payer (fax/upload/mail) with claim reference.<br>• Request reprocessing once form received.<br>• If patient refuses → inform payer; may bill patient directly or write off.</td></tr>
A43: CO 22 | B43: Covered by Another Payer | C43: M32 — Conditional Payment Made Pending Primary Payer Decision (Coordination of Benefits). | D43: The payer issued a conditional payment because another insurer is considered the primary payer, but payment was made temporarily to avoid delays in patient care or provider reimbursement. | E43: • Medicare makes a conditional payment while employer group health insurance is primary but has not yet processed the claim. • Auto insurance, workers’ compensation, or liability insurance is primary, but Medicare pays conditionally due to processing delays. • Patient has multiple insurance policies, and coordination of benefits was not finalized at time of billing. • Provider submits claim to Medicare without primary payer EOB, resulting in conditional payment issuance. • Primary insurance later pays the claim, requiring refund to the conditional payer. | F43: • Incorrect insurance order or incomplete • Coordination of Benefits (COB) information at registration. • Claim submitted to secondary payer before primary payer adjudication. • Failure to identify Medicare Secondary Payer situations (employment, liability, no-fault, workers’ compensation). • Missing primary payer EOB when billing secondary insurance. • Patient insurance information not updated or verified before claim submission. • Workflow gaps in tracking conditional payments and refund obligations. | G43: • Verify patient insurance hierarchy and determine the correct primary payer. • Bill the primary insurance if not already done and obtain the Explanation of Benefits (EOB). • Submit the primary payer EOB to the conditional payer (e.g., Medicare) for coordination and adjustment. • If payment received from primary after conditional payment → promptly refund the conditional payer to avoid recoupment penalties. • Update patient account to reflect correct payer responsibility. • If conditional payment was made appropriately and no other payer exists → provide documentation confirming no other coverage. | I43: <tr data-carc="CO 22" data-type="co" data-rarc="M32 — Conditional Payment Made Pending Primary Payer Decision (Coordination of Benefits)." data-denial="The payer issued a conditional payment because another insurer is considered the primary payer, but payment was made temporarily to avoid delays in patient care or provider reimbursement." data-root="• Incorrect insurance order or incomplete • Coordination of Benefits (COB) information at registration.\n• Claim submitted to secondary payer before primary payer adjudication.\n• Failure to identify Medicare Secondary Payer situations (employment, liability, no-fault, workers’ compensation).\n• Missing primary payer EOB when billing secondary insurance.\n• Patient insurance information not updated or verified before claim submission.\n• Workflow gaps in tracking conditional payments and refund obligations."><td><div class="row-num">#97</div><span class="carc-badge co">CO 22</span></td><td><span class="denial-reason">Covered by Another Payer</span></td><td class="rarc-wrap"><div class="rarc-id">M32</div><div class="rarc-desc">Conditional Payment Made Pending Primary Payer Decision (Coordination of Benefits).</div></td><td class="td-meaning">The payer issued a conditional payment because another insurer is considered the primary payer, but payment was made temporarily to avoid delays in patient care or provider reimbursement.</td><td><div class="chip-row"><span class="chip chip-green">Medicare makes a conditional payment while employer group health insurance is primary but has not yet processed the claim.</span><span class="chip chip-green">Auto insurance, workers’ compensation, or liability insurance is primary, but Medicare pays conditionally due to processing delays.</span><span class="chip chip-green">Patient has multiple insurance policies, and coordination of benefits was not finalized at time of billing.</span><span class="chip chip-green">Provider submits claim to Medicare without primary payer EOB, resulting in conditional payment issuance.</span><span class="chip chip-green">Primary insurance later pays the claim, requiring refund to the conditional payer.</span></div></td><td><div class="chip-row"><span class="chip chip-green">Incorrect insurance order or incomplete Coordination of Benefits (COB) information at registration.</span><span class="chip chip-green">Claim submitted to secondary payer before primary payer adjudication.</span><span class="chip chip-green">Failure to identify Medicare Secondary Payer situations (employment, liability, no-fault, workers’ compensation).</span><span class="chip chip-green">Missing primary payer EOB when billing secondary insurance.</span><span class="chip chip-green">Patient insurance information not updated or verified before claim submission.</span><span class="chip chip-green">Workflow gaps in tracking conditional payments and refund obligations.</span></div></td><td class="td-res">• Verify patient insurance hierarchy and determine the correct primary payer.<br>• Bill the primary insurance if not already done and obtain the Explanation of Benefits (EOB).<br>• Submit the primary payer EOB to the conditional payer (e.g., Medicare) for coordination and adjustment.<br>• If payment received from primary after conditional payment → promptly refund the conditional payer to avoid recoupment penalties.<br>• Update patient account to reflect correct payer responsibility.<br>• If conditional payment was made appropriately and no other payer exists → provide documentation confirming no other coverage.</td></tr>
A44: CO 109 | B44: Covered by Another Payer | C44: MA07—Alert: The claim information is also being forwarded to the patient's supplemental insurer. Send any questions regarding supplemental benefits to them. | D44: This alert indicates that the claim information has been automatically forwarded to Medicaid for secondary review and potential payment consideration. This typically occurs in Coordination of Benefits (COB) situations where Medicare or another primary payer has processed the claim and transmitted it to Medicaid as the secondary payer (commonly called a crossover claim). This is informational and not a denial. | E44: • Medicare processes claim for dual-eligible patient and forwards it to Medicaid automatically → MA07 appears. • Primary commercial payer sends crossover claim to Medicaid for secondary adjudication → informational alert issued. • Provider submits claim to Medicare only, and Medicare forwards to Medicaid per crossover agreement → no action needed initially. • Claim forwarded but Medicaid later denies due to eligibility or coverage limitations → separate Medicaid remittance received. • Incorrect Medicaid ID on file causing forwarding issues → Medicaid unable to process after crossover. | F44: • Normal coordination of benefits process for dual-eligible patients. • Automatic payer crossover agreement between primary payer and Medicaid. • Patient enrolled in both Medicare and Medicaid programs. • System-generated informational remark rather than an error condition. | G44: • Monitor for Medicaid remittance advice to determine secondary payment outcome. • Verify patient Medicaid eligibility and ID information if payment not received. • If Medicaid does not process claim → submit claim manually to Medicaid with primary EOB. • Reconcile payments once Medicaid adjudication is complete. • Contact Medicaid if crossover claim cannot be located. | I44: <tr data-carc="CO 109" data-type="co" data-rarc="MA07 — Alert: The claim information has also been forwarded to Medicaid for review." data-denial="This alert indicates that the claim information has been automatically forwarded to Medicaid for secondary review and potential payment consideration. This typically occurs in Coordination of Benefits (COB) situations where Medicare or another primary payer has processed the claim and transmitted it to Medicaid as the secondary payer (commonly called a crossover claim). This is informational and not a denial." data-root="• Normal coordination of benefits process for dual-eligible patients.\n• Automatic payer crossover agreement between primary payer and Medicaid.\n• Patient enrolled in both Medicare and Medicaid programs.\n• System-generated informational remark rather than an error condition."><td><div class="row-num">#138</div><span class="carc-badge co">CO 109</span></td><td><span class="denial-reason">Covered by Another Payer</span></td><td class="rarc-wrap"><div class="rarc-id">MA07</div><div class="rarc-desc">Alert: The claim information has also been forwarded to Medicaid for review.</div></td><td class="td-meaning">This alert indicates that the claim information has been automatically forwarded to Medicaid for secondary review and potential payment consideration. This typically occurs in Coordination of Benefits (COB) situations where Medicare or another primary payer has processed the claim and transmitted it to Medicaid as the secondary payer (commonly called a crossover claim). This is informational and not a denial.</td><td><div class="chip-row"><span class="chip chip-green">Medicare processes claim for dual-eligible patient and forwards it to Medicaid automatically → MA07 appears.</span><span class="chip chip-green">Primary commercial payer sends crossover claim to Medicaid for secondary adjudication → informational alert issued.</span><span class="chip chip-green">Provider submits claim to Medicare only, and Medicare forwards to Medicaid per crossover agreement → no action needed initially.</span><span class="chip chip-green">Claim forwarded but Medicaid later denies due to eligibility or coverage limitations → separate Medicaid remittance received.</span><span class="chip chip-green">Incorrect Medicaid ID on file causing forwarding issues → Medicaid unable to process after crossover.</span></div></td><td><div class="chip-row"><span class="chip chip-green">Normal coordination of benefits process for dual-eligible patients.</span><span class="chip chip-green">Automatic payer crossover agreement between primary payer and Medicaid.</span><span class="chip chip-green">Patient enrolled in both Medicare and Medicaid programs.</span><span class="chip chip-green">System-generated informational remark rather than an error condition.</span></div></td><td class="td-res">• Monitor for Medicaid remittance advice to determine secondary payment outcome.<br>• Verify patient Medicaid eligibility and ID information if payment not received.<br>• If Medicaid does not process claim → submit claim manually to Medicaid with primary EOB.<br>• Reconcile payments once Medicaid adjudication is complete.<br>• Contact Medicaid if crossover claim cannot be located.</td></tr>
A45: CO 109 | B45: Covered by Another Payer | C45: MA08—Alert: Information is being forwarded to the patient's supplemental insurer | D45: This alert indicates that the claim information was not automatically forwarded to a supplemental insurance plan because either: The patient’s supplemental coverage is not a Medigap plan eligible for Medicare crossover, or The provider does not participate with Medicare, so automatic forwarding cannot occur. As a result, the provider may need to submit the claim manually to the secondary or supplemental payer if additional reimbursement is expected. This is informational and not a denial. | E45: • Patient has commercial secondary insurance instead of Medigap → Medicare does not forward claim. • Provider is non-participating with Medicare → crossover not triggered. • Supplemental plan not enrolled in Medicare crossover program → claim not transmitted. • Medicare processes claim but provider expects automatic secondary billing → MA08 appears. • Incorrect supplemental payer information on file → forwarding fails. | F45: • Supplemental payer not eligible for Medicare crossover process. • Provider enrollment status preventing automatic forwarding. • Incorrect assumption that all secondary plans receive crossover claims. • Missing or incorrect secondary insurance information. • System limitations or payer configuration issues. | G45: • Verify patient secondary or supplemental insurance type. • Determine whether the plan participates in Medicare crossover. • If not forwarded automatically → submit claim manually to secondary payer with Medicare EOB. • Confirm provider participation status with Medicare if applicable. • Update insurance information if incorrect. • Track claim to ensure secondary adjudication occurs. | I45: <tr data-carc="CO 109" data-type="co" data-rarc="MA08 — Alert: Claim information was not forwarded because the supplemental coverage is not with a Medigap plan, or you do not participate in Medicare." data-denial="This alert indicates that the claim information was not automatically forwarded to a supplemental insurance plan because either:\n\nThe patient’s supplemental coverage is not a Medigap plan eligible for Medicare crossover, or\n\nThe provider does not participate with Medicare, so automatic forwarding cannot occur.\n\nAs a result, the provider may need to submit the claim manually to the secondary or supplemental payer if additional reimbursement is expected. This is informational and not a denial." data-root="• Supplemental payer not eligible for Medicare crossover process.\n• Provider enrollment status preventing automatic forwarding.\n• Incorrect assumption that all secondary plans receive crossover claims.\n• Missing or incorrect secondary insurance information.\n• System limitations or payer configuration issues."><td><div class="row-num">#139</div><span class="carc-badge co">CO 109</span></td><td><span class="denial-reason">Covered by Another Payer</span></td><td class="rarc-wrap"><div class="rarc-id">MA08</div><div class="rarc-desc">Alert: Claim information was not forwarded because the supplemental coverage is not with a Medigap plan, or you do not participate in Medicare.</div></td><td class="td-meaning">This alert indicates that the claim information was not automatically forwarded to a supplemental insurance plan because either:<br><br>The patient’s supplemental coverage is not a Medigap plan eligible for Medicare crossover, or<br><br>The provider does not participate with Medicare, so automatic forwarding cannot occur.<br><br>As a result, the provider may need to submit the claim manually to the secondary or supplemental payer if additional reimbursement is expected. This is informational and not a denial.</td><td><div class="chip-row"><span class="chip chip-green">Patient has commercial secondary insurance instead of Medigap → Medicare does not forward claim.</span><span class="chip chip-green">Provider is non-participating with Medicare → crossover not triggered.</span><span class="chip chip-green">Supplemental plan not enrolled in Medicare crossover program → claim not transmitted.</span><span class="chip chip-green">Medicare processes claim but provider expects automatic secondary billing → MA08 appears.</span><span class="chip chip-green">Incorrect supplemental payer information on file → forwarding fails.</span></div></td><td><div class="chip-row"><span class="chip chip-green">Supplemental payer not eligible for Medicare crossover process.</span><span class="chip chip-green">Provider enrollment status preventing automatic forwarding.</span><span class="chip chip-green">Incorrect assumption that all secondary plans receive crossover claims.</span><span class="chip chip-green">Missing or incorrect secondary insurance information.</span><span class="chip chip-green">System limitations or payer configuration issues.</span></div></td><td class="td-res">• Verify patient secondary or supplemental insurance type.<br>• Determine whether the plan participates in Medicare crossover.<br>• If not forwarded automatically → submit claim manually to secondary payer with Medicare EOB.<br>• Confirm provider participation status with Medicare if applicable.<br>• Update insurance information if incorrect.<br>• Track claim to ensure secondary adjudication occurs.</td></tr>
... A66: CO 4 | B66: Incorrect Billing Code for Service | C66: N34—Incorrect billing code for this service | D66: The claim was rejected because an incorrect billing code (CPT/HCPCS/revenue code) was used for the service provided. The code submitted does not accurately represent the procedure, service, or level of care performed, or it is not valid under payer guidelines. | E66: Wrong CPT code selected for procedure → claim rejected. Outdated or deleted code used → denial applied. Code does not match diagnosis or service → rejection issued. Incorrect modifier leading to wrong code interpretation → claim denied. Service billed under incorrect code category → claim unprocessable. | F66: Incorrect CPT/HCPCS/revenue code selection. Use of outdated or invalid codes. Mismatch between documentation and coding. Lack of coding knowledge or updates. Missing or incorrect modifiers. System or coding tool errors. | G66: Review clinical documentation for accurate service details. Identify correct CPT/HCPCS/revenue code. Ensure code aligns with diagnosis and payer guidelines. Apply appropriate modifiers if required. Update and resubmit corrected claim. Appeal if denial occurred despite correct coding. | I66: <tr data-carc="" data-type="" data-rarc="N34 — Incorrect claim form/format for this service." data-denial="" data-root=""><td><div class="row-num">#471</div><span class="carc-badge "></span></td><td><span class="denial-reason"></span></td><td class="rarc-wrap"><div class="rarc-id">N34</div><div class="rarc-desc">Incorrect claim form/format for this service.</div></td><td class="td-meaning"></td><td><div class="chip-row"></div></td><td><div class="chip-row"></div></td><td class="td-res"></td></tr>
A67: CO 4 | B67: Incorrect Level of Service | C67: M85—Physician evaluation and management services billed with the incorrect level of service | D67: The claim was denied or adjusted because the evaluation and management (E/M) service was billed with an incorrect level of service. This means the CPT code submitted (e.g., office visit level 3, 4, or 5) does not match the documentation, medical necessity, or coding guidelines. | E67: Level 4 visit billed but documentation supports only level 2 → downcoded/denied. High-level E/M billed without sufficient MDM complexity → rejection issued. Time-based billing not supported by documentation → denial applied. Incorrect E/M code selected for visit type (new vs established patient) → denied. Template-based documentation not supporting billed level → claim adjusted. | F67: Upcoding or incorrect E/M level selection. Insufficient or incomplete clinical documentation. Misunderstanding of E/M coding guidelines. Failure to apply 2021/2023 E/M rules (MDM/time-based). Use of incorrect patient type (new vs established). Lack of coding audit or validation process. | G67: Review clinical documentation to validate correct E/M level. Compare billed code with MDM or time-based criteria. Correct E/M code if overcoded or undercoded. Resubmit corrected claim. Educate provider on proper documentation requirements. Appeal if denial occurred despite appropriate documentation.
A68: CO 4 | B68: Incorrect Modifier(s) for the Service | C68: N35—Incorrect modifier(s) for this service | D68: The claim was rejected because the modifier(s) appended to the CPT/HCPCS code were incorrect, invalid, missing, or not appropriate for the service billed. Modifiers provide additional information about the service—such as distinct procedural service, multiple procedures, professional vs technical component, or special circumstances. If modifiers are incorrect or inconsistent with payer rules, the payer cannot accurately interpret the service, leading to claim rejection or denial. On the CMS-1500 claim form, modifiers are reported in Box 24D — CPT/HCPCS Codes (Modifier field). On the UB-04 claim form, modifiers are included in Form Locator (FL) 44 — HCPCS Codes, alongside | E68: Missing modifier required for distinct service (e.g., -59) → claim rejected. Incorrect modifier applied (e.g., -26 vs -TC) → denial applied. Multiple procedures billed without appropriate modifiers → rejection issued. Modifier not supported by payer policy → claim denied. Mismatch between modifier and documentation → claim unprocessable. | F68: Incorrect modifier selection. Missing required modifier. Use of outdated or invalid modifiers. Mismatch between documentation and modifier usage. Lack of knowledge of payer-specific modifier rules. Coding or system errors. | G68: Review clinical documentation for service details. Identify correct modifier(s) based on coding guidelines. Ensure modifier aligns with payer-specific rules. Update claim with appropriate modifier(s). Resubmit corrected claim. Appeal if denial occurred despite correct modifier usage. | I68: <tr data-carc="" data-type="" data-rarc="N35 — Program integrity/utilization review decision." data-denial="" data-root=""><td><div class="row-num">#482</div><span class="carc-badge "></span></td><td><span class="denial-reason"></span></td><td class="rarc-wrap"><div class="rarc-id">N35</div><div class="rarc-desc">Program integrity/utilization review decision.</div></td><td class="td-meaning"></td><td><div class="chip-row"></div></td><td><div class="chip-row"></div></td><td class="td-res"></td></tr>
A69: CO 16 | B69: Incorrect or Missing Revenue Code | C69: N520—Resubmit this claim/service with the correct Revenue Code | D69: The claim was rejected because the Revenue Code is missing, invalid, or incorrect for the billed service. Revenue codes are used to identify the department or type of service provided in institutional billing and must align with: HCPCS/CPT codes Type of service and billing guidelines On the UB-04 claim form, revenue codes are reported in: FL 42 (Revenue Code) They must correspond with: FL 44 (HCPCS/Rates) | E69: Incorrect revenue code for service type → rejected Missing revenue code on claim line → denial Revenue code does not match HCPCS → unprocessable | F69: Incorrect revenue code selection Missing revenue code during charge entry Mismatch between revenue code and procedure Outdated billing guidelines | G69: Review service and correct revenue code Ensure alignment with HCPCS/CPT code Update claim with valid revenue code Resubmit claim | I69: <tr data-carc="" data-type="" data-rarc="N520 — Alert: Payment made from a Consumer Spending Account." data-denial="" data-root=""><td><div class="row-num">#656</div><span class="carc-badge "></span></td><td><span class="denial-reason"></span></td><td class="rarc-wrap"><div class="rarc-id">N520</div><div class="rarc-desc">Alert: Payment made from a Consumer Spending Account.</div></td><td class="td-meaning"></td><td><div class="chip-row"></div></td><td><div class="chip-row"></div></td><td class="td-res"></td></tr>
A70: CO 16 | B70: Incorrect Patient Identifier | C70: N154—Alert: Incorrect patient identifier | D70: The claim was rejected because the patient identifier (e.g., member ID, Medicare Beneficiary Identifier (MBI), or policy number) submitted on the claim is incorrect. | E70: Incorrect member ID entered → claim rejected. Old or inactive policy number used → denial applied. Mismatch between patient name and identifier → rejection issued. MBI entered incorrectly (typo or format issue) → claim denied. System truncates or alters identifier → claim unprocessable. | F70: Data entry errors during registration. Outdated or incorrect insurance information. Failure to verify eligibility prior to billing. Mismatch between patient and insured details. System or EDI mapping errors. Incomplete demographic validation. | G70: Verify correct patient identifier from insurance card or eligibility portal. Update billing system with accurate member ID/MBI. Ensure consistency with patient name and DOB. Resubmit corrected claim. Confirm claim acceptance through clearinghouse or payer portal. | I70: <tr data-carc="" data-type="" data-rarc="N154 — Alert: This payment was delayed for correction of provider's mailing address." data-denial="" data-root=""><td><div class="row-num">#280</div><span class="carc-badge "></span></td><td><span class="denial-reason"></span></td><td class="rarc-wrap"><div class="rarc-id">N154</div><div class="rarc-desc">Alert: This payment was delayed for correction of provider's mailing address.</div></td><td class="td-meaning"></td><td><div class="chip-row"></div></td><td><div class="chip-row"></div></td><td class="td-res"></td></tr>
A71: CO 16 | B71: Incorrect Payer Submission | C71: N418—Misrouted claim. See the payer's claim submission instructions. | D71: The claim was rejected because it was sent to the wrong payer or incorrect payer channel, and does not align with the payer’s claim submission instructions. Each payer has defined rules for: Where to submit claims (primary vs secondary payer, correct insurance) How to submit claims (electronic vs paper, specific clearinghouse routes) What identifiers to use (payer ID, plan ID, claim type) If a claim is routed incorrectly—such as sending a primary claim to a secondary payer, or using the wrong payer ID or submission pathway—the payer will reject it as misrouted. | E71: Claim sent to wrong insurance payer → rejected as misrouted. Secondary claim submitted as primary without COB information → denial issued. Incorrect payer ID used in EDI submission → claim not recognized. Claim routed through wrong clearinghouse channel → rejected. Medicare claim mistakenly sent to commercial payer → unprocessable. | F71: Incorrect payer selection in billing system. Invalid or outdated payer ID. Missing or incorrect COB sequencing (primary vs secondary). Lack of understanding of payer submission rules. Front-end insurance verification errors. Clearinghouse routing configuration issues. | G71: Verify patient insurance details (primary, secondary, tertiary). Confirm correct payer ID and submission route. Check payer-specific billing instructions (EDI vs paper). Correct COB sequencing if applicable. Update claim with correct payer information. Resubmit claim to the appropriate payer. Validate claim acceptance via clearinghouse or payer portal. | I71: <tr data-carc="" data-type="" data-rarc="N418 — Misrouted claim. See the payer's claim submission instructions." data-denial="" data-root=""><td><div class="row-num">#553</div><span class="carc-badge "></span></td><td><span class="denial-reason"></span></td><td class="rarc-wrap"><div class="rarc-id">N418</div><div class="rarc-desc">Misrouted claim. See the payer's claim submission instructions.</div></td><td class="td-meaning"></td><td><div class="chip-row"></div></td><td><div class="chip-row"></div></td><td class="td-res"></td></tr>
A72: CO 16 | B72: Incorrect Procedure Code for Service/Date | C72: N56—Procedure code billed is not correct/valid for the services billed or the date of service billed | D72: The claim was denied because the procedure code (CPT/HCPCS) billed is not valid for the service performed or the date of service. This may occur if: The code is outdated or inactive The code does not match the service rendered The code is not valid for the DOS (e.g., deleted or replaced code) On the CMS-1500, procedure codes are reported in: Box 24D (CPT/HCPCS + Modifiers) On the UB-04, they are reported in: FL 44 (HCPCS/Rates) FL 74 (Procedure Code) | E72: Deleted CPT code used for current DOS → denied Incorrect code selected for service → rejection Code not valid for billing date → unprocessable | F72: Use of outdated CPT/HCPCS codes Coding errors during charge entry Lack of updated coding references System not updated with current code sets | G72: Verify correct CPT/HCPCS code for service and DOS Update to valid/current code Ensure proper modifiers if required Resubmit claim | I72: <tr data-carc="" data-type="" data-rarc="N56 — Procedure code billed is not correct/valid for the services billed or the date of service billed." data-denial="" data-root=""><td><div class="row-num">#696</div><span class="carc-badge "></span></td><td><span class="denial-reason"></span></td><td class="rarc-wrap"><div class="rarc-id">N56</div><div class="rarc-desc">Procedure code billed is not correct/valid for the services billed or the date of service billed.</div></td><td class="td-meaning"></td><td><div class="chip-row"></div></td><td><div class="chip-row"></div></td><td class="td-res"></td></tr>
A73: CO 16 | B73: Invalid Admission Date | C73: MA40—Alert: The patient overpaid you for these unassigned services. You must issue the patient a refund within 30 days for the amount paid that exceeds the charges. | D73: The admission date was missing, incomplete, invalid, or inconsistent with other reported dates. For institutional claims, the admission date establishes the start of the inpatient stay and is required to determine benefit period eligibility, covered days, deductible application, and reimbursement calculation. On the UB-04 claim form, the admission date is reported in Form Locator (FL) 12 — Admission Date. It must align with FL 6 — Statement Covers Period and related day counts (FL 7–10). The CMS-1500 form does not contain a dedicated admission date field for professional claims; services are reported per line in Box 24A — Date(s) of Service, | E73: • UB-04 claim submitted without FL 12 populated → rejected. • Admission date later than discharge date → denial applied. • Admission date inconsistent with billing period → claim unprocessable. • Incorrect date format entered → rejection issued. • System transmission error omitted admission date → denied. | F73: • UB-04 claim submitted without FL 12 populated → rejected. • Admission date later than discharge date → denial applied. • Admission date inconsistent with billing period → claim unprocessable. • Incorrect date format entered → rejection issued. • System transmission error omitted admission date → denied. | G73: • Verify correct admission date from medical records. • Ensure admission date falls within statement covers period. • Correct claim with accurate FL 12 entry. • Validate alignment with covered and coinsurance day counts. • Resubmit corrected claim. • Review clearinghouse acknowledgment for acceptance. | I73: <tr data-carc="" data-type="" data-rarc="MA40 — Missing/incomplete/invalid admission date." data-denial="" data-root=""><td><div class="row-num">#184</div><span class="carc-badge "></span></td><td><span class="denial-reason"></span></td><td class="rarc-wrap"><div class="rarc-id">MA40</div><div class="rarc-desc">Missing/incomplete/invalid admission date.</div></td><td class="td-meaning"></td><td><div class="chip-row"></div></td><td><div class="chip-row"></div></td><td class="td-res"></td></tr>
A74: CO 16 | B74: Invalid Admission Date | C74: MA34—Missing/incomplete/invalid admission date | D74: The claim was rejected because the admission date was missing, incomplete, invalid, or not properly reported. The admission date is a critical element for institutional (inpatient/outpatient) claims. On the UB-04 claim form, the admission date is reported in Form Locator (FL) 12 — Admission Date and must align with FL 6 — Statement Covers Period, FL 17 — Discharge Status, and other service details. | E74: Admission date field left blank → claim rejected. Invalid or future admission date entered → denial applied. Admission date later than discharge date → rejection issued. Mismatch between admission date and statement covers period → claim denied. System failed to populate admission date → claim unprocessable. | F74: Missing admission date during claim entry. Incorrect or invalid date format. Mismatch between clinical documentation and billing data. Staff unfamiliar with UB-04 requirements. System or EDI mapping errors. Incomplete validation before submission. | G74: Verify correct admission date from medical records. Ensure logical sequence (admission ≤ discharge). Align admission date with statement covers period and services billed. Update claim with accurate admission date. Resubmit corrected claim. Appeal if denial occurred despite correct data.
A75: CO 16 | B75: Invalid Admission Hour | C75: N48—Missing/incomplete/invalid admission hour | D75: The claim was rejected because the admission hour is missing, incomplete, or invalid, preventing accurate claim processing and validation of admission timing. Admission hour is required to: Determine billing accuracy (e.g., same-day discharge rules) Validate medical necessity and level of care Support timely admission documentation On the UB-04 claim form, admission hour is reported in: FL 13 (Admission Hour) | E75: Admission hour missing on inpatient claim → rejected Invalid hour format (not 00–23) → denial Mismatch between admission date and hour → unprocessable | F75: Missing data during registration Invalid or incorrect time format EDI mapping or system errors Lack of validation rules | G75: Verify admission details from patient records Enter correct admission hour (00–23 format) Update claim (FL 13 / EDI segment) Resubmit claim | I75: <tr data-carc="" data-type="" data-rarc="N48 — Claim information does not agree with information received from other insurance carrier." data-denial="" data-root=""><td><div class="row-num">#617</div><span class="carc-badge "></span></td><td><span class="denial-reason"></span></td><td class="rarc-wrap"><div class="rarc-id">N48</div><div class="rarc-desc">Claim information does not agree with information received from other insurance carrier.</div></td><td class="td-meaning"></td><td><div class="chip-row"></div></td><td><div class="chip-row"></div></td><td class="td-res"></td></tr>
A76: CO 16 | B76: Invalid Admission Source | C76: MA42—Alert: This is not a Medicare-approved ambulance service area. | D76: The admission source (Point of Origin) was missing, incomplete, invalid, or inconsistent with other admission details. Admission source identifies where the patient was admitted from (e.g., physician referral, transfer from hospital, emergency room, SNF, home, etc.) and is required for institutional inpatient claim processing.On the UB-04 claim form, admission source is reported in Form Locator (FL) 15 — Point of Origin for Admission or Visit. It must align with FL 12 — Admission Date, FL 14 — Type of Admission, and FL 6 — Statement Covers Period. The CMS-1500 form does not contain a dedicated admission source field. | E76: • UB-04 claim submitted with FL 15 blank → rejected. • Invalid admission source code entered → denial applied. • Admission source inconsistent with transfer billing → rejection issued. • Patient transferred from SNF but coded as physician referral → claim unprocessable. • System transmission error omitted FL 15 → denied. | F76: • Admission source field not populated during billing. • Incorrect coding selection during registration. • Mismatch between clinical intake documentation and billing data. • Staff unfamiliar with admission source codes. • System mapping or EDI transmission errors. • Incomplete transfer documentation. | G76: • Verify correct admission source from admission records. • Ensure FL 15 code matches clinical documentation. • Confirm consistency with admission type and transfer status. • Correct claim and resubmit. • Review clearinghouse acknowledgment for acceptance. | I76: <tr data-carc="" data-type="" data-rarc="MA42 — Missing/incomplete/invalid admission source." data-denial="" data-root=""><td><div class="row-num">#186</div><span class="carc-badge "></span></td><td><span class="denial-reason"></span></td><td class="rarc-wrap"><div class="rarc-id">MA42</div><div class="rarc-desc">Missing/incomplete/invalid admission source.</div></td><td class="td-meaning"></td><td><div class="chip-row"></div></td><td><div class="chip-row"></div></td><td class="td-res"></td></tr>
A77: CO 16 | B77: Invalid Admission Type | C77: MA41 — Missing/incomplete/invalid admission type. | D77: The admission type was missing, incomplete, invalid, or inconsistent with the reported services. Admission type identifies whether the patient was admitted as emergency, urgent, elective, newborn, trauma, etc., and is required for institutional claim adjudication. On the UB-04 claim form, admission type is reported in Form Locator (FL) 14 — Type of Admission. It must align with FL 12 — Admission Date, FL 15 — Point of Origin, and FL 6 — Statement Covers Period. The CMS-1500 form does not contain a dedicated admission type field. | E77: • UB-04 claim submitted with FL 14 blank → rejected. • Invalid admission type code entered → denial applied. • Admission type inconsistent with revenue codes (e.g., elective coded as emergency) → rejection issued. • Incorrect mapping from hospital system to billing system → claim unprocessable. • System transmission error omitted admission type → denied. | F77: • Admission type field not populated during claim creation. • Incorrect coding selection by registration staff. • Mismatch between clinical documentation and billing data. • Staff unfamiliar with admission type code definitions. • System configuration or mapping errors. • Incomplete patient intake documentation. | G77: • Verify correct admission type from admission records. • Ensure code selection aligns with clinical documentation. • Correct FL 14 entry on UB-04 claim. • Confirm consistency with admission date and origin fields. • Resubmit corrected claim. • Review clearinghouse acknowledgment for acceptance. | I77: <tr data-carc="" data-type="" data-rarc="MA41 — Missing/incomplete/invalid admission type." data-denial="" data-root=""><td><div class="row-num">#185</div><span class="carc-badge "></span></td><td><span class="denial-reason"></span></td><td class="rarc-wrap"><div class="rarc-id">MA41</div><div class="rarc-desc">Missing/incomplete/invalid admission type.</div></td><td class="td-meaning"></td><td><div class="chip-row"></div></td><td><div class="chip-row"></div></td><td class="td-res"></td></tr>
A78: CO 16 | B78: Invalid Admission Type | C78: N445—Missing/incomplete/invalid admission type | D78: The claim was rejected because the admission type is missing, incomplete, invalid, or incorrectly reported. Admission type indicates the circumstances under which a patient was admitted (e.g., emergency, urgent, elective, newborn, trauma). Payers use this information to: Determine medical necessity Validate billing classification Apply appropriate reimbursement rules If the admission type is absent or invalid, the payer cannot correctly adjudicate the claim. On the UB-04 claim form, admission type is reported in: FL 14 (Type of Admission) | E78: Inpatient claim submitted without admission type → rejected. Invalid admission type code (not recognized by payer) → denial. Admission type inconsistent with diagnosis (e.g., elective for emergency condition) → rejection. Missing admission details in EDI CL1 segment → claim unprocessable. System defaulted incorrect admission type → denial issued. | F78: Missing admission type in claim form or EDI. Use of invalid or outdated admission type codes. Incorrect data entry during patient registration. Mismatch between clinical documentation and billing data. EDI mapping or system configuration issues. Lack of validation rules for institutional claims. | G78: Review patient admission records. Identify correct admission type (e.g., emergency, urgent, elective). Update claim: UB-04 FL 14 EDI CL1 segment Ensure consistency with diagnosis and clinical documentation. Validate code against payer requirements. Resubmit corrected claim. Confirm acceptance via payer or clearinghouse. | I78: <tr data-carc="" data-type="" data-rarc="N445 — Missing document for actual cost or paid amount." data-denial="" data-root=""><td><div class="row-num">#580</div><span class="carc-badge "></span></td><td><span class="denial-reason"></span></td><td class="rarc-wrap"><div class="rarc-id">N445</div><div class="rarc-desc">Missing document for actual cost or paid amount.</div></td><td class="td-meaning"></td><td><div class="chip-row"></div></td><td><div class="chip-row"></div></td><td class="td-res"></td></tr>
A79: CO 16 | B79: Invalid Amount Due from Primary Payer | C79: N260—Missing/incomplete/invalid amount due from the primary payer | D79: The claim was rejected because the amount paid or due from the primary payer was missing, incomplete, invalid, or not properly reported. In Coordination of Benefits (COB) situations, secondary payers require accurate information about what the primary payer paid and what remains unpaid in order to calculate their payment responsibility. Without the correct primary payer amount, the secondary payer cannot determine remaining liability, patient responsibility, or coordination rules, resulting in claim rejection. | E79: • Secondary claim submitted without primary payment amount → claim rejected. • Incorrect amount entered from primary EOB → denial applied. • COB indicates prior payer but amount missing → rejection issued. • Mismatch between EOB and claim payment amount → claim denied. • System failed to transmit primary payer amount → claim unprocessable. | F79: • Secondary claim submitted without primary payment amount → claim rejected. • Incorrect amount entered from primary EOB → denial applied. • COB indicates prior payer but amount missing → rejection issued. • Mismatch between EOB and claim payment amount → claim denied. • System failed to transmit primary payer amount → claim unprocessable. | G79: • Obtain primary payer EOB and verify payment amount. • Ensure accuracy of amount paid and remaining balance. • Update claim with correct primary payer payment details. • Align COB data with EOB information. • Resubmit corrected claim. • Confirm claim acceptance through clearinghouse or payer portal. | I79: <tr data-carc="" data-type="" data-rarc="N260 — Missing/incomplete/invalid billing provider/supplier contact information." data-denial="" data-root=""><td><div class="row-num">#387</div><span class="carc-badge "></span></td><td><span class="denial-reason"></span></td><td class="rarc-wrap"><div class="rarc-id">N260</div><div class="rarc-desc">Missing/incomplete/invalid billing provider/supplier contact information.</div></td><td class="td-meaning"></td><td><div class="chip-row"></div></td><td><div class="chip-row"></div></td><td class="td-res"></td></tr>
A80: CO 16 | B80: Invalid Anesthesia Physical Status Modifier/Units | C80: N201—Missing/incomplete/invalid Anesthesia Physical Status modifier/modifying units. | D80: The claim was rejected because the anesthesia physical status modifier (P1–P6) and/or associated modifying units were missing, incomplete, invalid, or not properly reported. These modifiers indicate the patient’s pre-anesthesia health condition and risk level, which can impact reimbursement calculations. Payers use this information along with base units and time units to determine total anesthesia payment. Without valid physical status modifiers or units, the claim cannot be accurately processed. | E80: Anesthesia claim submitted without physical status modifier → rejected. Invalid modifier (e.g., incorrect P-level) → denial applied. Modifier documented but not included in claim → rejection issued. Incorrect modifying units assigned → claim adjusted or denied. System failed to transmit modifier data → claim unprocessable. | F80: Anesthesia claim submitted without physical status modifier → rejected. Invalid modifier (e.g., incorrect P-level) → denial applied. Modifier documented but not included in claim → rejection issued. Incorrect modifying units assigned → claim adjusted or denied. System failed to transmit modifier data → claim unprocessable. | G80: Missing anesthesia physical status modifier. Incorrect or invalid modifier selection (P1–P6). Mismatch between documentation and billed modifier. Staff unaware of anesthesia modifier requirements. System or EDI mapping errors. Incomplete anesthesia documentation.
A81: CO 16 | B81: Invalid Anesthesia Start/End Time | C81: N200—Missing/incomplete/invalid anesthesia start/end time | D81: The claim was rejected or adjusted because the anesthesia start and/or end time was missing, incomplete, invalid, or not properly documented. Accurate reporting of anesthesia start and stop times is essential to calculate total anesthesia time and corresponding units, which directly impacts reimbursement. Without valid time documentation, the payer cannot verify the duration of anesthesia services or determine appropriate payment. | E81: Anesthesia start time missing → claim rejected. End time not documented → denial applied. Start/end times inconsistent or illogical → rejection issued. Units billed without supporting time documentation → claim denied. System failed to transmit anesthesia time data → claim unprocessable. | F81: Anesthesia start time missing → claim rejected. End time not documented → denial applied. Start/end times inconsistent or illogical → rejection issued. Units billed without supporting time documentation → claim denied. System failed to transmit anesthesia time data → claim unprocessable. | G81: Review anesthesia record for accurate start and end times. Ensure time documentation is complete and valid. Recalculate anesthesia units based on correct time. Update claim with accurate information. Resubmit corrected claim. Appeal if denial occurred despite proper documentation. | I81: <tr data-carc="" data-type="" data-rarc="N200 — The professional component must be billed separately." data-denial="" data-root=""><td><div class="row-num">#323</div><span class="carc-badge "></span></td><td><span class="denial-reason"></span></td><td class="rarc-wrap"><div class="rarc-id">N200</div><div class="rarc-desc">The professional component must be billed separately.</div></td><td class="td-meaning"></td><td><div class="chip-row"></div></td><td><div class="chip-row"></div></td><td class="td-res"></td></tr>
A82: CO 16 | B82: Invalid Anesthesia Time/Units | C82: N199—Missing/incomplete/invalid anesthesia time/units | D82: The claim was rejected or adjusted because the anesthesia time or units reported were missing, incomplete, invalid, or not properly calculated. Anesthesia services are reimbursed based on time units (typically in minutes) combined with base units, and accurate reporting is essential for proper payment. If the time is not documented correctly, not converted into units properly, or does not align with payer guidelines, the claim cannot be processed. | E82: Anesthesia time not entered → claim rejected. Incorrect conversion of minutes to units → denial applied. Start/stop time missing in documentation → rejection issued. Units reported do not match documented time → claim denied. System failed to transmit anesthesia units → claim unprocessable. | F82: Missing anesthesia time documentation. Incorrect calculation of time units. Mismatch between documentation and billed units. Staff unfamiliar with anesthesia billing rules. System or EDI mapping errors. Incomplete anesthesia records. | G82: Missing anesthesia time documentation. Incorrect calculation of time units. Mismatch between documentation and billed units. Staff unfamiliar with anesthesia billing rules. System or EDI mapping errors. Incomplete anesthesia records. | I82: <tr data-carc="" data-type="" data-rarc="N199 — Additional payment/recoupment approved based on payer-initiated review/audit." data-denial="" data-root=""><td><div class="row-num">#320</div><span class="carc-badge "></span></td><td><span class="denial-reason"></span></td><td class="rarc-wrap"><div class="rarc-id">N199</div><div class="rarc-desc">Additional payment/recoupment approved based on payer-initiated review/audit.</div></td><td class="td-meaning"></td><td><div class="chip-row"></div></td><td><div class="chip-row"></div></td><td class="td-res"></td></tr>
A83: CO 16 | B83: Invalid Assignment of Benefits (AOB) Indicator | C83: N379—Missing/incomplete/invalid assignment of benefits indicator | D83: The claim was rejected because the Assignment of Benefits (AOB) indicator was missing, incomplete, invalid, or not properly reported. The AOB indicator specifies whether the patient has authorized the payer to send payment directly to the provider instead of the patient. Without a valid AOB indicator, the payer cannot determine who should receive payment (provider vs patient), which impacts claim processing and reimbursement routing. On the CMS-1500 claim form, the AOB indicator is reported in Box 27 — Accept Assignment? (Yes/No). | E83: Assignment indicator left blank → claim rejected. Invalid value entered (not Yes/No) → denial applied. Mismatch between AOB indicator and payer records → rejection issued. Provider expects direct payment but AOB not indicated → claim denied. System failed to transmit AOB indicator → claim unprocessable. | F83: Missing AOB indicator during claim entry. Incorrect or invalid assignment value. Mismatch between billing system and payer requirements. Staff unaware of assignment requirements. System or EDI mapping errors. | G83: Verify assignment of benefits status from patient authorization records. Ensure correct AOB indicator (Yes/No). Update claim with valid assignment information in Box 27. Resubmit corrected claim. Confirm claim acceptance through clearinghouse or payer portal. | I83: <tr data-carc="" data-type="" data-rarc="N379 — Claim level information does not match line level information." data-denial="" data-root=""><td><div class="row-num">#511</div><span class="carc-badge "></span></td><td><span class="denial-reason"></span></td><td class="rarc-wrap"><div class="rarc-id">N379</div><div class="rarc-desc">Claim level information does not match line level information.</div></td><td class="td-meaning"></td><td><div class="chip-row"></div></td><td><div class="chip-row"></div></td><td class="td-res"></td></tr>
A84: CO 16 | B84: Invalid Attending Physician or Provider Information | C84: M106—Missing/incomplete/invalid attending physician or provider information | D84: The claim was rejected because the attending physician or provider information was missing, incomplete, invalid, or not properly reported. On the UB-04 claim form, the attending provider is reported in Form Locator (FL) 76 — Attending Provider Name and Identifiers (including NPI), On the CMS-1500 claim form, while there is no specific “attending” field, related provider roles are reported in Box 24J — Rendering Provider NPI and Box 17 — Referring/Ordering Provider, depending on the service context. | E84: Attending physician NPI missing in FL 76 → claim rejected. Invalid or inactive provider identifier submitted → denial applied. Incorrect provider listed as attending (e.g., consulting instead of attending) → rejection issued. System failed to populate attending provider field → claim unprocessable. Mismatch between attending provider and medical records → denied. | F84: Attending provider field left blank during claim creation. Incorrect or outdated provider information. Provider not enrolled or inactive with payer. Staff unaware of attending provider requirements. System mapping or interface errors. Mismatch between clinical documentation and billing data. | G84: Verify correct attending provider from medical records. Ensure valid NPI and provider details are entered in FL 76. Confirm provider is enrolled and active with payer. Update claim with accurate attending provider information. Resubmit corrected claim. Appeal if denial occurred despite correct information.
A85: CO 16 | B85: Invalid Attending Provider Information | C85: N113—Missing/incomplete/invalid attending provider information | D85: The claim was rejected because the attending provider information (such as name, NPI, or other required identifiers) was missing, incomplete, invalid, or not properly reported. On the UB-04 claim form, the attending provider is reported in Form Locator (FL) 76 — Attending Provider Name and Identifiers (including NPI), which must be complete and valid. On the CMS-1500 claim form, related provider roles are reported in Box 24J — Rendering Provider NPI and Box 17 — Referring/Ordering Provider, depending on the service context. | E85: Attending provider field left blank in FL 76 → claim rejected. Invalid or inactive attending provider NPI → denial applied. Incorrect provider listed as attending → rejection issued. Mismatch between attending provider and medical records → claim denied. System failed to populate attending provider field → claim unprocessable. | F85: Missing attending provider information during claim entry. Incorrect or outdated provider identifiers. Provider not enrolled or inactive with payer. Staff unaware of attending provider requirements. System or EDI mapping errors. Mismatch between clinical documentation and billing data. | G85: Verify attending provider details from medical records. Ensure correct and valid NPI is entered in FL 76. Confirm provider enrollment and active status with payer. Update claim with accurate attending provider information. Resubmit corrected claim. Appeal if denial occurred despite valid information. | I85: <tr data-carc="" data-type="" data-rarc="N113 — Only one initial visit is covered per physician, group practice or provider." data-denial="" data-root=""><td><div class="row-num">#243</div><span class="carc-badge "></span></td><td><span class="denial-reason"></span></td><td class="rarc-wrap"><div class="rarc-id">N113</div><div class="rarc-desc">Only one initial visit is covered per physician, group practice or provider.</div></td><td class="td-meaning"></td><td><div class="chip-row"></div></td><td><div class="chip-row"></div></td><td class="td-res"></td></tr>
A86: CO 16 | B86: Invalid Attending, Ordering, Operating, or Referring Physician Identification | C86: M68—Missing/incomplete/invalid attending, ordering, operating, or referring physician identification | D86: The claim was rejected because the identification details (such as name, NPI, or other required identifiers) for one or more provider roles—attending, ordering, operating, or referring physician—were missing, incomplete. On the CMS-1500 claim form, provider information is reported in Box 17 — Referring/Ordering Provider, Box 17b — NPI, and Box 24J — Rendering Provider NPI. On the UB-04 claim form, provider roles are reported in Form Locator (FL) 76 — Attending Provider, FL 77 — Operating Physician, and FL 78–79 — Other Providers (including ordering/referring), which must be accurately completed. | E86: Attending provider NPI missing in FL 76 → claim rejected. Ordering physician not listed for lab/radiology service → denial applied. Operating physician field blank for surgical procedure → rejection issued. Invalid or inactive NPI submitted → claim denied. Mismatch between provider roles and documentation → claim unprocessable. | F86: Missing provider identifiers during claim entry. Incorrect or outdated NPI used. Provider not enrolled or inactive with payer. Staff unaware of required provider roles. System or EDI mapping errors. Mismatch between clinical documentation and billing data. | G86: Verify correct provider roles from medical records. Ensure valid NPIs are entered for all required providers. Confirm provider enrollment and active status with payer. Update claim with accurate provider information. Resubmit corrected claim. Appeal if denial occurred despite valid data.
A87: CO 197 | B87: Invalid Authorization | C87: N752—Alert: Payment adjusted based on program integrity review | D87: The claim was denied because the HIPPS Treatment Authorization Code (TAC) — a 5-character code from OASIS (home health) or MDS (SNF) assessment — is missing, incomplete (wrong format/length), or invalid (expired, wrong grouping, not matching assessment). Required for Medicare home health (TOB 32x) and SNF PPS (TOB 21x/18x) claims to determine payment group. | E87: • Home health claim (TOB 329) billed without 5-character HIPPS TAC from OASIS → denied. • SNF claim (TOB 211) missing HIPPS from 5-day MDS assessment. • TAC incomplete (4 characters) or invalid (mismatched assessment date/grouping). | F87: • HIPPS TAC not generated or pulled from finalized OASIS/MDS before billing. • Assessment not completed/transmitted or locked before claim submission. • Billing software failed to populate HIPPS TAC from assessment data. • Timing error: Claim submitted before TAC available (e.g., early billing). | G87: • Retrieve correct HIPPS TAC from finalized OASIS (home health) or MDS (SNF) in assessment software or iQIES. • Correct/add valid 5-character TAC in claim (UB-04 FL 67 or 837I Loop 2400 SV202-7). • Resubmit corrected claim (frequency 7). • If TAC invalid due to assessment error → correct OASIS/MDS and resubmit both. • Appeal with OASIS/MDS summary or TAC printout if misapplied. | I87: <tr data-carc="CO 16" data-type="co" data-rarc="N752 — Missing/incomplete/invalid HIPPS Treatment Authorization Code (TAC)." data-denial="The claim was denied because the HIPPS Treatment Authorization Code (TAC) — a 5-character code from OASIS (home health) or MDS (SNF) assessment — is missing, incomplete (wrong format/length), or invalid (expired, wrong grouping, not matching assessment). Required for Medicare home health (TOB 32x) and SNF PPS (TOB 21x/18x) claims to determine payment group." data-root="• HIPPS TAC not generated or pulled from finalized OASIS/MDS before billing.\n• Assessment not completed/transmitted or locked before claim submission.\n• Billing software failed to populate HIPPS TAC from assessment data.\n• Timing error: Claim submitted before TAC available (e.g., early billing)."><td><div class="row-num">#34</div><span class="carc-badge co">CO 16</span></td><td><span class="denial-reason">Invalid Authorization</span></td><td class="rarc-wrap"><div class="rarc-id">N752</div><div class="rarc-desc">Missing/incomplete/invalid HIPPS Treatment Authorization Code (TAC).</div></td><td class="td-meaning">The claim was denied because the HIPPS Treatment Authorization Code (TAC) — a 5-character code from OASIS (home health) or MDS (SNF) assessment — is missing, incomplete (wrong format/length), or invalid (expired, wrong grouping, not matching assessment). Required for Medicare home health (TOB 32x) and SNF PPS (TOB 21x/18x) claims to determine payment group.</td><td><div class="chip-row"><span class="chip chip-green">Home health claim (TOB 329) billed without 5-character HIPPS TAC from OASIS → denied.</span><span class="chip chip-green">SNF claim (TOB 211) missing HIPPS from 5-day MDS assessment.</span><span class="chip chip-green">TAC incomplete (4 characters) or invalid (mismatched assessment date/grouping).</span></div></td><td><div class="chip-row"><span class="chip chip-green">HIPPS TAC not generated or pulled from finalized OASIS/MDS before billing.</span><span class="chip chip-green">Assessment not completed/transmitted or locked before claim submission.</span><span class="chip chip-green">Billing software failed to populate HIPPS TAC from assessment data.</span><span class="chip chip-green">Timing error: Claim submitted before TAC available (e.g., early billing).</span></div></td><td class="td-res">• Retrieve correct HIPPS TAC from finalized OASIS (home health) or MDS (SNF) in assessment software or iQIES.<br>• Correct/add valid 5-character TAC in claim (UB-04 FL 67 or 837I Loop 2400 SV202-7).<br>• Resubmit corrected claim (frequency 7).<br>• If TAC invalid due to assessment error → correct OASIS/MDS and resubmit both.<br>• Appeal with OASIS/MDS summary or TAC printout if misapplied.</td></tr>
A88: CO 197 | B88: Invalid Authorization | C88: M62—Missing/incomplete/invalid treatment authorization code | D88: The claim was denied because the required treatment authorization code (prior authorization number, precertification number, referral number, or authorization number) is missing, incomplete (wrong format, missing digits), or invalid (expired, wrong payer format, not matching service/date). Required for services needing pre-approval (surgery, imaging, therapy, DME, specialty visits, inpatient). On the CMS-1500 claim form, authorization information is typically reported in Box 23 — Prior Authorization Number. On the UB-04 claim form, authorization numbers are reported in Form Locator (FL) 63 — Treatment Authorization Code. | E88: • Elective surgery (knee replacement) billed without prior authorization number. • MRI/CT or advanced imaging denied – missing precertification code. • PT/OT sessions beyond initial limit billed without updated authorization number. • DME (CPAP, wheelchair) submitted without payer authorization/reference number. | F88: • No prior authorization obtained before rendering service. • Authorization number not entered or entered incorrectly on claim. • Expired authorization (service date outside approved period). • Format mismatch (payer requires specific length/alphanumeric pattern). • Billing software/manual entry omitted authorization field. | G88: • Review EOB/ERA and claim to confirm authorization issue. • Check payer portal or contact payer to verify current/valid authorization. • Correct/add valid authorization number (CMS-1500 Box 23 or 837P REF segment). • Resubmit corrected claim (frequency 7). • If retroactive authorization possible → obtain and resubmit. • Appeal with authorization letter or medical necessity notes if denied incorrectly. | I88: <tr data-carc="CO 16" data-type="co" data-rarc="M62 — Missing/incomplete/invalid treatment authorization code." data-denial="The claim was denied because the required treatment authorization code (prior authorization number, precertification number, referral number, or authorization number) is missing, incomplete (wrong format, missing digits), or invalid (expired, wrong payer format, not matching service/date). Required for services needing pre-approval (surgery, imaging, therapy, DME, specialty visits, inpatient). On the CMS-1500 claim form, authorization information is typically reported in Box 23 — Prior Authorization Number. On the UB-04 claim form, authorization numbers are reported in Form Locator (FL) 63 — Treatment Authorization Code." data-root="• No prior authorization obtained before rendering service.\n• Authorization number not entered or entered incorrectly on claim.\n• Expired authorization (service date outside approved period).\n• Format mismatch (payer requires specific length/alphanumeric pattern).\n• Billing software/manual entry omitted authorization field."><td><div class="row-num">#27</div><span class="carc-badge co">CO 16</span></td><td><span class="denial-reason">Invalid Authorization</span></td><td class="rarc-wrap"><div class="rarc-id">M62</div><div class="rarc-desc">Missing/incomplete/invalid treatment authorization code.</div></td><td class="td-meaning">The claim was denied because the required treatment authorization code (prior authorization number, precertification number, referral number, or authorization number) is missing, incomplete (wrong format, missing digits), or invalid (expired, wrong payer format, not matching service/date). Required for services needing pre-approval (surgery, imaging, therapy, DME, specialty visits, inpatient). On the CMS-1500 claim form, authorization information is typically reported in Box 23 — Prior Authorization Number. On the UB-04 claim form, authorization numbers are reported in Form Locator (FL) 63 — Treatment Authorization Code.</td><td><div class="chip-row"><span class="chip chip-green">Elective surgery (knee replacement) billed without prior authorization number.</span><span class="chip chip-green">MRI/CT or advanced imaging denied – missing precertification code.</span><span class="chip chip-green">PT/OT sessions beyond initial limit billed without updated authorization number.</span><span class="chip chip-green">DME (CPAP, wheelchair) submitted without payer authorization/reference number.</span></div></td><td><div class="chip-row"><span class="chip chip-green">No prior authorization obtained before rendering service.</span><span class="chip chip-green">Authorization number not entered or entered incorrectly on claim.</span><span class="chip chip-green">Expired authorization (service date outside approved period).</span><span class="chip chip-green">Format mismatch (payer requires specific length/alphanumeric pattern).</span><span class="chip chip-green">Billing software/manual entry omitted authorization field.</span></div></td><td class="td-res">• Review EOB/ERA and claim to confirm authorization issue.<br>• Check payer portal or contact payer to verify current/valid authorization.<br>• Correct/add valid authorization number (CMS-1500 Box 23 or 837P REF segment).<br>• Resubmit corrected claim (frequency 7).<br>• If retroactive authorization possible → obtain and resubmit.<br>• Appeal with authorization letter or medical necessity notes if denied incorrectly.</td></tr>
A89: CO 16 | B89: Invalid Authorization | C89: N311—Not covered unless the diagnosis reported requires treatment | D89: The claim was denied or adjusted because the authorized/anticipated return-to-work date (or release-to-work date) is missing, incomplete (partial date), or invalid (future date, before injury/onset, illogical sequence). Required mainly on workers' comp, no-fault, disability, or occupational health claims (often UB-04 occurrence span code/date or 837I equivalent). | E89: • Workers' comp follow-up therapy claim missing authorized return-to-work date. • Disability/occupational health service denied – return date future or after discharge. • No-fault/auto liability claim rejected – incomplete return-to-work date (month/year only). | F89: • Return-to-work date field (UB-04 occurrence span or 837I equivalent) left blank. • Invalid date (future, before injury, illogical vs. DOS/principal). • Format error (partial date, wrong order). • Provider notes lack clear return-to-work date from treating physician. | G89: • Review UB-04 occurrence/date fields (or 837I loops) and progress notes for return-to-work date. • Correct/add accurate date from records (must be logical vs. injury/DOS). • Resubmit corrected claim (frequency 7). • Appeal with dated notes (progress notes, work status report) showing return timeline. • Contact payer adjuster for exact field/format required. | I89: <tr data-carc="CO 16" data-type="co" data-rarc="N311 — Missing/incomplete/invalid authorized to return to work date." data-denial="The claim was denied or adjusted because the authorized/anticipated return-to-work date (or release-to-work date) is missing, incomplete (partial date), or invalid (future date, before injury/onset, illogical sequence). Required mainly on workers' comp, no-fault, disability, or occupational health claims (often UB-04 occurrence span code/date or 837I equivalent)." data-root="• Return-to-work date field (UB-04 occurrence span or 837I equivalent) left blank.\n• Invalid date (future, before injury, illogical vs. DOS/principal).\n• Format error (partial date, wrong order).\n• Provider notes lack clear return-to-work date from treating physician."><td><div class="row-num">#29</div><span class="carc-badge co">CO 16</span></td><td><span class="denial-reason">Invalid Authorization</span></td><td class="rarc-wrap"><div class="rarc-id">N311</div><div class="rarc-desc">Missing/incomplete/invalid authorized to return to work date.</div></td><td class="td-meaning">The claim was denied or adjusted because the authorized/anticipated return-to-work date (or release-to-work date) is missing, incomplete (partial date), or invalid (future date, before injury/onset, illogical sequence). Required mainly on workers' comp, no-fault, disability, or occupational health claims (often UB-04 occurrence span code/date or 837I equivalent).</td><td><div class="chip-row"><span class="chip chip-green">Workers' comp follow-up therapy claim missing authorized return-to-work date.</span><span class="chip chip-green">Disability/occupational health service denied – return date future or after discharge.</span><span class="chip chip-green">No-fault/auto liability claim rejected – incomplete return-to-work date (month/year only).</span></div></td><td><div class="chip-row"><span class="chip chip-green">Return-to-work date field (UB-04 occurrence span or 837I equivalent) left blank.</span><span class="chip chip-green">Invalid date (future, before injury, illogical vs. DOS/principal).</span><span class="chip chip-green">Format error (partial date, wrong order).</span><span class="chip chip-green">Provider notes lack clear return-to-work date from treating physician.</span></div></td><td class="td-res">• Review UB-04 occurrence/date fields (or 837I loops) and progress notes for return-to-work date.<br>• Correct/add accurate date from records (must be logical vs. injury/DOS).<br>• Resubmit corrected claim (frequency 7).<br>• Appeal with dated notes (progress notes, work status report) showing return timeline.<br>• Contact payer adjuster for exact field/format required.</td></tr>
A90: CO 197 | B90: Invalid Authorization | C90: N54—Missing/incomplete/invalid point of drop-off information | D90: The claim was denied or adjusted because the billed services, codes, units, dates, diagnosis, place of service, or other details do not match the pre-certification, prior authorization, or approved referral on file with the payer. | E90: • Authorization for 12 PT visits; claim billed 20 visits → excess denied. • MRI authorized for lumbar spine only; claim included cervical → partial/full denial. • Inpatient stay pre-certified for 3 days; claim billed 5 days → extra days denied. • Referral to specialist authorized; claim included unauthorized add-on test → denied. | F90: • Billed services/units/codes/dates deviate from exact authorization approval. • Authorization obtained but limited scope not followed during billing. • No additional authorization requested when services expanded. • Clerical mismatch: Claim details not matching authorization letter. | G90: • Review EOB/ERA, claim, and authorization letter to identify exact inconsistency. • Compare billed elements against approved authorization (codes, units, dates, Dx). • Correct claim to match authorization and resubmit (frequency 7). • If exceeded → obtain retroactive/additional authorization and resubmit. • Appeal with authorization letter + clinical notes justifying deviation if allowed. | I90: <tr data-carc="CO 197" data-type="co" data-rarc="N54 — Claim information is inconsistent with pre-certified/authorized services." data-denial="The claim was denied or adjusted because the billed services, codes, units, dates, diagnosis, place of service, or other details do not match the pre-certification, prior authorization, or approved referral on file with the payer." data-root="• Billed services/units/codes/dates deviate from exact authorization approval.\n• Authorization obtained but limited scope not followed during billing.\n• No additional authorization requested when services expanded.\n• Clerical mismatch: Claim details not matching authorization letter."><td><div class="row-num">#30</div><span class="carc-badge co">CO 197</span></td><td><span class="denial-reason">Invalid Authorization</span></td><td class="rarc-wrap"><div class="rarc-id">N54</div><div class="rarc-desc">Claim information is inconsistent with pre-certified/authorized services.</div></td><td class="td-meaning">The claim was denied or adjusted because the billed services, codes, units, dates, diagnosis, place of service, or other details do not match the pre-certification, prior authorization, or approved referral on file with the payer.</td><td><div class="chip-row"><span class="chip chip-green">Authorization for 12 PT visits; claim billed 20 visits → excess denied.</span><span class="chip chip-green">MRI authorized for lumbar spine only; claim included cervical → partial/full denial.</span><span class="chip chip-green">Inpatient stay pre-certified for 3 days; claim billed 5 days → extra days denied.</span><span class="chip chip-green">Referral to specialist authorized; claim included unauthorized add-on test → denied.</span></div></td><td><div class="chip-row"><span class="chip chip-green">Billed services/units/codes/dates deviate from exact authorization approval.</span><span class="chip chip-green">Authorization obtained but limited scope not followed during billing.</span><span class="chip chip-green">No additional authorization requested when services expanded.</span><span class="chip chip-green">Clerical mismatch: Claim details not matching authorization letter.</span></div></td><td class="td-res">• Review EOB/ERA, claim, and authorization letter to identify exact inconsistency.<br>• Compare billed elements against approved authorization (codes, units, dates, Dx).<br>• Correct claim to match authorization and resubmit (frequency 7).<br>• If exceeded → obtain retroactive/additional authorization and resubmit.<br>• Appeal with authorization letter + clinical notes justifying deviation if allowed.</td></tr>
A91: CO 16 | B91: Invalid Beginning and Ending Dates | C91: MA31—Missing/incomplete/invalid beginning and ending dates of the period billed | D91: The beginning and/or ending dates of the billing period were missing, incomplete, invalid, or inconsistent. Institutional claims and certain professional services require accurate “from” and “through” dates to define the period being billed. On the UB-04 claim form, the billing period is reported in Form Locator (FL) 6 — Statement Covers Period (From/Through Dates). On the CMS-1500 claim form, service dates are reported at the line level in Box 24A — Date(s) of Service (From/To), which must reflect accurate beginning and ending dates for the services billed. | E91: • UB-04 claim submitted without “through” date in FL 6 → rejected. • Invalid date format entered in statement covers period → denial applied. • Service line dates inconsistent with billing period → claim unprocessable. • “From” date later than “through” date → rejection issued. • System transmission dropped one of the date fields → claim denied. | F91: • Date fields left blank during claim creation. • Data entry or formatting errors. • Mismatch between service line dates and billing period. • Staff unfamiliar with statement covers period requirements. • System mapping or clearinghouse errors. Incomplete documentation from facility records. | G91: • Verify correct beginning and ending dates from medical records. • Ensure date span accurately reflects services rendered. • Correct claim with proper date format and sequence. • Confirm consistency between header and line-level dates. • Resubmit corrected claim. • Review clearinghouse acknowledgment for acceptance. | I91: <tr data-carc="" data-type="" data-rarc="MA31 — Missing/incomplete/invalid beginning and ending dates of the period billed." data-denial="" data-root=""><td><div class="row-num">#176</div><span class="carc-badge "></span></td><td><span class="denial-reason"></span></td><td class="rarc-wrap"><div class="rarc-id">MA31</div><div class="rarc-desc">Missing/incomplete/invalid beginning and ending dates of the period billed.</div></td><td class="td-meaning"></td><td><div class="chip-row"></div></td><td><div class="chip-row"></div></td><td class="td-res"></td></tr>
A92: CO 16 | B92: Invalid Billing | C92: MA107—Not covered unless rent-to-purchase or rent threshold is met | D92: The claim was denied because the paper CMS-1500 claim form Field 19 (Additional Claim Information) contained more than three separate data items, exceeding payer processing limitations. Field 19 is used to report supplemental information such as narrative descriptions, authorization notes, or special billing indicators when required. On the CMS-1500 claim form, this information is reported in Box 19 — Additional Claim Information. The UB-04 claim form does not have a direct equivalent to Box 19; supplemental information is typically conveyed through appropriate form locators (such as FL 80 — Remarks). | E92: • Paper claim submitted with multiple notes, authorization numbers, and narratives all in Box 19 → denied. • Provider includes excessive billing instructions in Field 19 → rejection issued. • Multiple identifiers entered in one field without formatting → denial applied. • Manual paper claim used instead of electronic submission causing field overflow → payer rejects claim. • Clearinghouse conversion to paper format resulted in excessive information in Box 19 → denied. | F92: • Too many data elements entered in Box 19 on paper claim. • Staff unaware of payer limitation on number of items allowed. • Use of paper claim instead of electronic claim submission. • Improper formatting of information within field. • System or workflow requiring multiple notes without proper separation. | G92: • Review information entered in Box 19 and determine required elements only. • Limit entries to allowable number of data items per payer rules. • Move additional information to attachments or supporting documentation if needed. • Resubmit claim with corrected Field 19 content. • Consider electronic claim submission to avoid field limitations. • Appeal if denial applied incorrectly and field usage was compliant. | I92: <tr data-carc="CO 16" data-type="co" data-rarc="MA107 — Paper claim contains more than three separate data items in field 19." data-denial="The claim was denied because the paper CMS-1500 claim form Field 19 (Additional Claim Information) contained more than three separate data items, exceeding payer processing limitations. Field 19 is used to report supplemental information such as narrative descriptions, authorization notes, or special billing indicators when required. On the CMS-1500 claim form, this information is reported in Box 19 — Additional Claim Information. The UB-04 claim form does not have a direct equivalent to Box 19; supplemental information is typically conveyed through appropriate form locators (such as FL 80 — Remarks)." data-root="• Too many data elements entered in Box 19 on paper claim.\n• Staff unaware of payer limitation on number of items allowed.\n• Use of paper claim instead of electronic claim submission.\n• Improper formatting of information within field.\n• System or workflow requiring multiple notes without proper separation."><td><div class="row-num">#141</div><span class="carc-badge co">CO 16</span></td><td><span class="denial-reason">Invalid Billing</span></td><td class="rarc-wrap"><div class="rarc-id">MA107</div><div class="rarc-desc">Paper claim contains more than three separate data items in field 19.</div></td><td class="td-meaning">The claim was denied because the paper CMS-1500 claim form Field 19 (Additional Claim Information) contained more than three separate data items, exceeding payer processing limitations. Field 19 is used to report supplemental information such as narrative descriptions, authorization notes, or special billing indicators when required. On the CMS-1500 claim form, this information is reported in Box 19 — Additional Claim Information. The UB-04 claim form does not have a direct equivalent to Box 19; supplemental information is typically conveyed through appropriate form locators (such as FL 80 — Remarks).</td><td><div class="chip-row"><span class="chip chip-green">Paper claim submitted with multiple notes, authorization numbers, and narratives all in Box 19 → denied.</span><span class="chip chip-green">Provider includes excessive billing instructions in Field 19 → rejection issued.</span><span class="chip chip-green">Multiple identifiers entered in one field without formatting → denial applied.</span><span class="chip chip-green">Manual paper claim used instead of electronic submission causing field overflow → payer rejects claim.</span><span class="chip chip-green">Clearinghouse conversion to paper format resulted in excessive information in Box 19 → denied.</span></div></td><td><div class="chip-row"><span class="chip chip-green">Too many data elements entered in Box 19 on paper claim.</span><span class="chip chip-green">Staff unaware of payer limitation on number of items allowed.</span><span class="chip chip-green">Use of paper claim instead of electronic claim submission.</span><span class="chip chip-green">Improper formatting of information within field.</span><span class="chip chip-green">System or workflow requiring multiple notes without proper separation.</span></div></td><td class="td-res">• Review information entered in Box 19 and determine required elements only.<br>• Limit entries to allowable number of data items per payer rules.<br>• Move additional information to attachments or supporting documentation if needed.<br>• Resubmit claim with corrected Field 19 content.<br>• Consider electronic claim submission to avoid field limitations.<br>• Appeal if denial applied incorrectly and field usage was compliant.</td></tr>
